{"skeleton":{"hash":"VaB9EgEcFYF9HTg10kzugOzg7NU","spine":"3.0.12","width":0,"height":0,"images":"./images3/"},"bones":[{"name":"root"},{"name":"R_arm_2","parent":"root","x":13.35,"y":77.32},{"name":"bone15","parent":"R_arm_2","x":-100.42,"y":-40.48},{"name":"bone16","parent":"bone15","length":20.74,"x":14.47,"y":4.42,"rotation":91.17},{"name":"R_arm_1","parent":"root","x":16.02,"y":98.72},{"name":"bone11","parent":"R_arm_1","x":-100.13,"y":35.43},{"name":"bone12","parent":"bone11","length":27.99,"x":-1.15,"y":-14.21,"rotation":166.79},{"name":"MAIN","parent":"root","y":57.59},{"name":"L_arm_2","parent":"root","x":18.69,"y":77.32},{"name":"bone7","parent":"L_arm_2","x":23,"y":-35.98},{"name":"bone8","parent":"bone7","length":27.42,"x":-15.33,"y":-0.82,"rotation":91.98},{"name":"L_arm_1","parent":"root","x":7.12,"y":98.51},{"name":"bone3","parent":"L_arm_1","x":45.71,"y":33.18},{"name":"bone4","parent":"bone3","length":24.11,"x":-0.31,"y":-13.27,"rotation":5.26},{"name":"EF3","parent":"root","x":628.63,"y":182.59,"scaleX":1.5,"scaleY":1.5},{"name":"EF2","parent":"root","x":583.03,"y":182.59,"scaleX":1.5,"scaleY":1.5},{"name":"EF1","parent":"root","x":538.78,"y":182.59,"scaleX":1.5,"scaleY":1.5}],"slots":[{"name":"MAIN","bone":"MAIN","attachment":"idle_00"},{"name":"R_fire2_00","bone":"bone16","attachment":"R_fire2_00"},{"name":"L_fire2_00","bone":"bone8","attachment":"L_fire2_00"},{"name":"R_fire1_00","bone":"bone12","attachment":"R_fire1_00"},{"name":"L_fire1_00","bone":"bone4","attachment":"L_fire1_00"},{"name":"EF/EF_idle/ef_00","bone":"EF1","blend":"additive"},{"name":"EF/EF_idle/ef_0","bone":"EF2","blend":"additive"},{"name":"EF/EF_idle/ef_1","bone":"EF3","blend":"additive"}],"skins":{"default":{"EF/EF_idle/ef_0":{"EF/EF_idle/ef_00":{"x":-2.26,"y":-23.72,"width":293,"height":141},"EF/EF_idle/ef_05":{"x":-2.28,"y":-23.72,"width":293,"height":141},"EF/EF_idle/ef_06":{"x":-2.28,"y":-23.72,"width":293,"height":141},"EF/EF_idle/ef_07":{"x":-2.28,"y":-23.72,"width":293,"height":141},"EF/EF_idle/ef_08":{"x":-2.28,"y":-23.72,"width":293,"height":141},"EF/EF_idle/ef_09":{"x":-2.28,"y":-23.72,"width":293,"height":141},"EF/EF_idle/ef_10":{"x":-2.28,"y":-23.72,"width":293,"height":141},"EF/EF_idle/ef_11":{"x":-2.28,"y":-23.72,"width":293,"height":141},"EF/EF_idle/ef_12":{"x":-2.28,"y":-23.72,"width":293,"height":141},"EF/EF_idle/ef_13":{"x":-2.28,"y":-23.72,"width":293,"height":141},"EF/EF_idle/ef_14":{"x":-2.28,"y":-23.72,"width":293,"height":141},"EF/EF_idle/ef_15":{"x":-2.28,"y":-23.72,"width":293,"height":141},"EF/EF_idle/ef_16":{"x":-2.28,"y":-23.72,"width":293,"height":141},"EF/EF_idle/ef_17":{"x":-2.28,"y":-23.72,"width":293,"height":141},"EF/EF_idle/ef_18":{"x":-2.28,"y":-23.72,"width":293,"height":141},"EF/EF_idle/ef_19":{"x":-2.28,"y":-23.72,"width":293,"height":141},"EF/EF_idle/ef_20":{"x":-2.28,"y":-23.72,"width":293,"height":141},"EF/EF_idle/ef_21":{"x":-2.28,"y":-23.72,"width":293,"height":141},"EF/EF_idle/ef_22":{"x":-2.28,"y":-23.72,"width":293,"height":141},"EF/EF_idle/ef_23":{"x":-2.28,"y":-23.72,"width":293,"height":141},"EF/EF_idle/ef_24":{"x":-2.28,"y":-23.72,"width":293,"height":141},"EF/EF_idle/ef_25":{"x":-2.28,"y":-23.72,"width":293,"height":141},"EF/EF_idle/ef_26":{"x":-2.28,"y":-23.72,"width":293,"height":141},"EF/EF_idle/ef_27":{"x":-2.28,"y":-23.72,"width":293,"height":141},"EF/EF_idle/ef_28":{"x":-2.28,"y":-23.72,"width":293,"height":141},"EF/EF_idle/ef_29":{"x":-2.28,"y":-23.72,"width":293,"height":141},"EF/EF_idle/ef_31":{"x":-2.28,"y":-23.72,"width":293,"height":141},"EF/EF_idle/ef_33":{"x":-2.28,"y":-23.72,"width":293,"height":141},"EF/EF_idle/ef_35":{"x":-2.28,"y":-23.72,"width":293,"height":141}},"EF/EF_idle/ef_00":{"EF/EF_idle/ef_00":{"x":-2.26,"y":-23.72,"width":293,"height":141},"EF/EF_idle/ef_05":{"x":-2.28,"y":-23.72,"width":293,"height":141},"EF/EF_idle/ef_06":{"x":-2.28,"y":-23.72,"width":293,"height":141},"EF/EF_idle/ef_07":{"x":-2.28,"y":-23.72,"width":293,"height":141},"EF/EF_idle/ef_08":{"x":-2.28,"y":-23.72,"width":293,"height":141},"EF/EF_idle/ef_09":{"x":-2.28,"y":-23.72,"width":293,"height":141},"EF/EF_idle/ef_10":{"x":-2.28,"y":-23.72,"width":293,"height":141},"EF/EF_idle/ef_11":{"x":-2.28,"y":-23.72,"width":293,"height":141},"EF/EF_idle/ef_12":{"x":-2.28,"y":-23.72,"width":293,"height":141},"EF/EF_idle/ef_13":{"x":-2.28,"y":-23.72,"width":293,"height":141},"EF/EF_idle/ef_14":{"x":-2.28,"y":-23.72,"width":293,"height":141},"EF/EF_idle/ef_15":{"x":-2.28,"y":-23.72,"width":293,"height":141},"EF/EF_idle/ef_16":{"x":-2.28,"y":-23.72,"width":293,"height":141},"EF/EF_idle/ef_17":{"x":-2.28,"y":-23.72,"width":293,"height":141},"EF/EF_idle/ef_18":{"x":-2.28,"y":-23.72,"width":293,"height":141},"EF/EF_idle/ef_19":{"x":-2.28,"y":-23.72,"width":293,"height":141},"EF/EF_idle/ef_20":{"x":-2.28,"y":-23.72,"width":293,"height":141},"EF/EF_idle/ef_21":{"x":-2.28,"y":-23.72,"width":293,"height":141},"EF/EF_idle/ef_22":{"x":-2.28,"y":-23.72,"width":293,"height":141},"EF/EF_idle/ef_23":{"x":-2.28,"y":-23.72,"width":293,"height":141},"EF/EF_idle/ef_24":{"x":-2.28,"y":-23.72,"width":293,"height":141},"EF/EF_idle/ef_25":{"x":-2.28,"y":-23.72,"width":293,"height":141},"EF/EF_idle/ef_26":{"x":-2.28,"y":-23.72,"width":293,"height":141},"EF/EF_idle/ef_27":{"x":-2.28,"y":-23.72,"width":293,"height":141},"EF/EF_idle/ef_28":{"x":-2.28,"y":-23.72,"width":293,"height":141},"EF/EF_idle/ef_29":{"x":-2.28,"y":-23.72,"width":293,"height":141},"EF/EF_idle/ef_31":{"x":-2.28,"y":-23.72,"width":293,"height":141},"EF/EF_idle/ef_33":{"x":-2.28,"y":-23.72,"width":293,"height":141},"EF/EF_idle/ef_35":{"x":-2.28,"y":-23.72,"width":293,"height":141}},"EF/EF_idle/ef_1":{"EF/EF_idle/ef_00":{"x":-2.26,"y":-23.72,"width":293,"height":141},"EF/EF_idle/ef_05":{"x":-2.28,"y":-23.72,"width":293,"height":141},"EF/EF_idle/ef_06":{"x":-2.28,"y":-23.72,"width":293,"height":141},"EF/EF_idle/ef_07":{"x":-2.28,"y":-23.72,"width":293,"height":141},"EF/EF_idle/ef_08":{"x":-2.28,"y":-23.72,"width":293,"height":141},"EF/EF_idle/ef_09":{"x":-2.28,"y":-23.72,"width":293,"height":141},"EF/EF_idle/ef_10":{"x":-2.28,"y":-23.72,"width":293,"height":141},"EF/EF_idle/ef_11":{"x":-2.28,"y":-23.72,"width":293,"height":141},"EF/EF_idle/ef_12":{"x":-2.28,"y":-23.72,"width":293,"height":141},"EF/EF_idle/ef_13":{"x":-2.28,"y":-23.72,"width":293,"height":141},"EF/EF_idle/ef_14":{"x":-2.28,"y":-23.72,"width":293,"height":141},"EF/EF_idle/ef_15":{"x":-2.28,"y":-23.72,"width":293,"height":141},"EF/EF_idle/ef_16":{"x":-2.28,"y":-23.72,"width":293,"height":141},"EF/EF_idle/ef_17":{"x":-2.28,"y":-23.72,"width":293,"height":141},"EF/EF_idle/ef_18":{"x":-2.28,"y":-23.72,"width":293,"height":141},"EF/EF_idle/ef_19":{"x":-2.28,"y":-23.72,"width":293,"height":141},"EF/EF_idle/ef_20":{"x":-2.28,"y":-23.72,"width":293,"height":141},"EF/EF_idle/ef_21":{"x":-2.28,"y":-23.72,"width":293,"height":141},"EF/EF_idle/ef_22":{"x":-2.28,"y":-23.72,"width":293,"height":141},"EF/EF_idle/ef_23":{"x":-2.28,"y":-23.72,"width":293,"height":141},"EF/EF_idle/ef_24":{"x":-2.28,"y":-23.72,"width":293,"height":141},"EF/EF_idle/ef_25":{"x":-2.28,"y":-23.72,"width":293,"height":141},"EF/EF_idle/ef_26":{"x":-2.28,"y":-23.72,"width":293,"height":141},"EF/EF_idle/ef_27":{"x":-2.28,"y":-23.72,"width":293,"height":141},"EF/EF_idle/ef_28":{"x":-2.28,"y":-23.72,"width":293,"height":141},"EF/EF_idle/ef_29":{"x":-2.28,"y":-23.72,"width":293,"height":141},"EF/EF_idle/ef_31":{"x":-2.28,"y":-23.72,"width":293,"height":141},"EF/EF_idle/ef_33":{"x":-2.28,"y":-23.72,"width":293,"height":141},"EF/EF_idle/ef_35":{"x":-2.28,"y":-23.72,"width":293,"height":141}},"L_fire1_00":{"L_fire1_00":{"x":-47.03,"y":-15.67,"rotation":-5.26,"width":310,"height":282},"L_fire1_01":{"x":-47.03,"y":-15.67,"rotation":-5.26,"width":310,"height":282},"L_fire1_02":{"x":-47.03,"y":-15.67,"rotation":-5.26,"width":310,"height":282},"L_fire1_03":{"x":-47.03,"y":-15.67,"rotation":-5.26,"width":310,"height":282},"L_fire1_04":{"x":-47.03,"y":-15.67,"rotation":-5.26,"width":310,"height":282},"L_fire1_05":{"x":-47.03,"y":-15.67,"rotation":-5.26,"width":310,"height":282},"L_fire1_06":{"x":-47.03,"y":-15.67,"rotation":-5.26,"width":310,"height":282},"L_fire1_07":{"x":-47.03,"y":-15.67,"rotation":-5.26,"width":310,"height":282}},"L_fire2_00":{"L_fire2_00":{"x":53.35,"y":9.07,"rotation":-91.94,"width":310,"height":282},"L_fire2_01":{"x":53.23,"y":5.84,"rotation":-91.94,"width":310,"height":282},"L_fire2_02":{"x":53.23,"y":5.84,"rotation":-91.94,"width":310,"height":282},"L_fire2_03":{"x":53.23,"y":5.84,"rotation":-91.94,"width":310,"height":282},"L_fire2_04":{"x":53.23,"y":5.84,"rotation":-91.94,"width":310,"height":282},"L_fire2_05":{"x":53.23,"y":5.84,"rotation":-91.94,"width":310,"height":282},"L_fire2_06":{"x":53.23,"y":5.84,"rotation":-91.94,"width":310,"height":282},"L_fire2_07":{"x":53.23,"y":5.84,"rotation":-91.94,"width":310,"height":282}},"MAIN":{"idle_00":{"x":8.5,"y":42.02,"width":465,"height":423},"idle_01":{"x":8.5,"y":42.02,"width":465,"height":423},"idle_02":{"x":8.5,"y":42.02,"width":465,"height":423},"idle_03":{"x":8.5,"y":42.02,"width":465,"height":423},"idle_04":{"x":8.5,"y":42.02,"width":465,"height":423}},"R_fire1_00":{"R_fire1_00":{"x":-88.32,"y":1.05,"rotation":-166.74,"width":310,"height":282},"R_fire1_01":{"x":-88.33,"y":1.05,"rotation":-166.74,"width":310,"height":282},"R_fire1_02":{"x":-88.33,"y":1.05,"rotation":-166.74,"width":310,"height":282},"R_fire1_03":{"x":-88.33,"y":1.05,"rotation":-166.74,"width":310,"height":282},"R_fire1_04":{"x":-88.33,"y":1.05,"rotation":-166.74,"width":310,"height":282},"R_fire1_05":{"x":-88.33,"y":1.05,"rotation":-166.74,"width":310,"height":282},"R_fire1_06":{"x":-88.33,"y":1.05,"rotation":-166.74,"width":310,"height":282},"R_fire1_07":{"x":-88.33,"y":1.05,"rotation":-166.74,"width":310,"height":282}},"R_fire2_00":{"R_fire2_00":{"x":34.09,"y":-95.74,"rotation":-91.17,"width":310,"height":282},"R_fire2_01":{"x":34.28,"y":-86.67,"rotation":-91.17,"width":310,"height":282},"R_fire2_02":{"x":34.28,"y":-86.67,"rotation":-91.17,"width":310,"height":282},"R_fire2_03":{"x":34.28,"y":-86.67,"rotation":-91.17,"width":310,"height":282},"R_fire2_04":{"x":34.28,"y":-86.67,"rotation":-91.17,"width":310,"height":282},"R_fire2_05":{"x":34.28,"y":-86.67,"rotation":-91.17,"width":310,"height":282},"R_fire2_06":{"x":34.28,"y":-86.67,"rotation":-91.17,"width":310,"height":282},"R_fire2_07":{"x":34.28,"y":-86.67,"rotation":-91.17,"width":310,"height":282}}}},"events":{"Event":{},"Hit":{},"HitEffect":{},"Sound1":{},"Sound2":{},"Sound3":{},"Voice":{}},"animations":{"idle":{"slots":{"EF/EF_idle/ef_00":{"attachment":[{"time":0,"name":"EF/EF_idle/ef_00"},{"time":0.0333,"name":"EF/EF_idle/ef_05"},{"time":0.0666,"name":"EF/EF_idle/ef_06"},{"time":0.1,"name":"EF/EF_idle/ef_07"},{"time":0.1666,"name":"EF/EF_idle/ef_08"},{"time":0.2333,"name":"EF/EF_idle/ef_09"},{"time":0.3,"name":"EF/EF_idle/ef_10"},{"time":0.3666,"name":"EF/EF_idle/ef_11"},{"time":0.4333,"name":"EF/EF_idle/ef_12"},{"time":0.5,"name":"EF/EF_idle/ef_13"},{"time":0.5666,"name":"EF/EF_idle/ef_14"},{"time":0.6333,"name":"EF/EF_idle/ef_15"},{"time":0.7,"name":"EF/EF_idle/ef_16"},{"time":0.7666,"name":"EF/EF_idle/ef_17"},{"time":0.8333,"name":"EF/EF_idle/ef_18"},{"time":0.9,"name":"EF/EF_idle/ef_19"},{"time":0.9666,"name":"EF/EF_idle/ef_20"},{"time":1.0333,"name":"EF/EF_idle/ef_21"},{"time":1.1,"name":"EF/EF_idle/ef_22"},{"time":1.1666,"name":"EF/EF_idle/ef_23"},{"time":1.2333,"name":"EF/EF_idle/ef_24"},{"time":1.3,"name":"EF/EF_idle/ef_25"},{"time":1.3666,"name":"EF/EF_idle/ef_26"},{"time":1.4,"name":"EF/EF_idle/ef_27"},{"time":1.4333,"name":"EF/EF_idle/ef_28"},{"time":1.4666,"name":"EF/EF_idle/ef_29"},{"time":1.5,"name":"EF/EF_idle/ef_31"},{"time":1.5333,"name":"EF/EF_idle/ef_33"},{"time":1.5666,"name":"EF/EF_idle/ef_35"},{"time":1.6,"name":null}],"color":[{"time":0,"color":"ffffff00"},{"time":0.1666,"color":"ffffffff"},{"time":0.3,"color":"ffffff24"},{"time":0.4,"color":"ffffffff"},{"time":0.5333,"color":"ffffff24","curve":"stepped"},{"time":0.9333,"color":"ffffff24"},{"time":1.0666,"color":"ffffffff"},{"time":1.2,"color":"ffffff24"},{"time":1.3333,"color":"ffffffff"},{"time":1.4666,"color":"ffffff24"},{"time":1.6,"color":"ffffffff"}]},"EF/EF_idle/ef_0":{"attachment":[{"time":0.1666,"name":"EF/EF_idle/ef_00"},{"time":0.2,"name":"EF/EF_idle/ef_05"},{"time":0.2333,"name":"EF/EF_idle/ef_06"},{"time":0.2666,"name":"EF/EF_idle/ef_07"},{"time":0.3333,"name":"EF/EF_idle/ef_08"},{"time":0.4,"name":"EF/EF_idle/ef_09"},{"time":0.4666,"name":"EF/EF_idle/ef_10"},{"time":0.5333,"name":"EF/EF_idle/ef_11"},{"time":0.6,"name":"EF/EF_idle/ef_12"},{"time":0.6666,"name":"EF/EF_idle/ef_13"},{"time":0.7333,"name":"EF/EF_idle/ef_14"},{"time":0.8,"name":"EF/EF_idle/ef_15"},{"time":0.8666,"name":"EF/EF_idle/ef_16"},{"time":0.9333,"name":"EF/EF_idle/ef_17"},{"time":1,"name":"EF/EF_idle/ef_18"},{"time":1.0666,"name":"EF/EF_idle/ef_19"},{"time":1.1333,"name":"EF/EF_idle/ef_20"},{"time":1.2,"name":"EF/EF_idle/ef_21"},{"time":1.2666,"name":"EF/EF_idle/ef_22"},{"time":1.3333,"name":"EF/EF_idle/ef_23"},{"time":1.4,"name":"EF/EF_idle/ef_24"},{"time":1.4666,"name":"EF/EF_idle/ef_25"},{"time":1.5333,"name":"EF/EF_idle/ef_26"},{"time":1.5666,"name":"EF/EF_idle/ef_27"},{"time":1.6,"name":"EF/EF_idle/ef_28"},{"time":1.6333,"name":"EF/EF_idle/ef_29"},{"time":1.6666,"name":"EF/EF_idle/ef_31"},{"time":1.7,"name":"EF/EF_idle/ef_33"},{"time":1.7333,"name":"EF/EF_idle/ef_35"},{"time":1.7666,"name":null}],"color":[{"time":0.1666,"color":"ffffff7b"},{"time":0.4333,"color":"ffffffff"},{"time":0.6333,"color":"ffffff1a","curve":"stepped"},{"time":1.0333,"color":"ffffff1a"},{"time":1.1666,"color":"ffffffff"},{"time":1.3,"color":"ffffff2d"},{"time":1.4333,"color":"ffffffff"},{"time":1.5666,"color":"ffffff2d"},{"time":1.7,"color":"ffffffff"},{"time":1.8333,"color":"ffffff2d"}]},"EF/EF_idle/ef_1":{"attachment":[{"time":0.3333,"name":"EF/EF_idle/ef_00"},{"time":0.3666,"name":"EF/EF_idle/ef_05"},{"time":0.4,"name":"EF/EF_idle/ef_06"},{"time":0.4333,"name":"EF/EF_idle/ef_07"},{"time":0.5,"name":"EF/EF_idle/ef_08"},{"time":0.5666,"name":"EF/EF_idle/ef_09"},{"time":0.6333,"name":"EF/EF_idle/ef_10"},{"time":0.7,"name":"EF/EF_idle/ef_11"},{"time":0.7666,"name":"EF/EF_idle/ef_12"},{"time":0.8333,"name":"EF/EF_idle/ef_13"},{"time":0.9,"name":"EF/EF_idle/ef_14"},{"time":0.9666,"name":"EF/EF_idle/ef_15"},{"time":1.0333,"name":"EF/EF_idle/ef_16"},{"time":1.1,"name":"EF/EF_idle/ef_17"},{"time":1.1666,"name":"EF/EF_idle/ef_18"},{"time":1.2333,"name":"EF/EF_idle/ef_19"},{"time":1.3,"name":"EF/EF_idle/ef_20"},{"time":1.3666,"name":"EF/EF_idle/ef_21"},{"time":1.4333,"name":"EF/EF_idle/ef_22"},{"time":1.5,"name":"EF/EF_idle/ef_23"},{"time":1.5666,"name":"EF/EF_idle/ef_24"},{"time":1.6333,"name":"EF/EF_idle/ef_25"},{"time":1.7,"name":"EF/EF_idle/ef_26"},{"time":1.7333,"name":"EF/EF_idle/ef_27"},{"time":1.7666,"name":"EF/EF_idle/ef_28"},{"time":1.8,"name":"EF/EF_idle/ef_29"},{"time":1.8333,"name":"EF/EF_idle/ef_31"},{"time":1.8666,"name":"EF/EF_idle/ef_33"},{"time":1.9,"name":"EF/EF_idle/ef_35"},{"time":1.9333,"name":null}],"color":[{"time":0.3333,"color":"ffffff00"},{"time":0.6,"color":"ffffffff"},{"time":0.7333,"color":"ffffff21","curve":"stepped"},{"time":1.1333,"color":"ffffff21"},{"time":1.2666,"color":"ffffffff"},{"time":1.4,"color":"ffffff2e"},{"time":1.5333,"color":"ffffffff"},{"time":1.6666,"color":"ffffff2e"},{"time":1.8,"color":"ffffffff"},{"time":1.9333,"color":"ffffff2e"}]},"L_fire1_00":{"attachment":[{"time":0,"name":"L_fire1_00"},{"time":0.0666,"name":"L_fire1_01"},{"time":0.1333,"name":"L_fire1_02"},{"time":0.2,"name":"L_fire1_03"},{"time":0.2666,"name":"L_fire1_04"},{"time":0.3333,"name":"L_fire1_05"},{"time":0.4,"name":"L_fire1_06"},{"time":0.4666,"name":"L_fire1_07"},{"time":0.5333,"name":"L_fire1_00"},{"time":0.6,"name":"L_fire1_01"},{"time":0.6666,"name":"L_fire1_02"},{"time":0.7333,"name":"L_fire1_03"},{"time":0.8,"name":"L_fire1_04"},{"time":0.8666,"name":"L_fire1_05"},{"time":0.9333,"name":"L_fire1_06"},{"time":1,"name":"L_fire1_07"},{"time":1.0666,"name":"L_fire1_00"},{"time":1.1333,"name":"L_fire1_01"},{"time":1.2,"name":"L_fire1_02"},{"time":1.2666,"name":"L_fire1_03"},{"time":1.3333,"name":"L_fire1_04"},{"time":1.4,"name":"L_fire1_05"},{"time":1.4666,"name":"L_fire1_06"},{"time":1.5333,"name":"L_fire1_07"},{"time":1.6,"name":"L_fire1_00"},{"time":1.6666,"name":"L_fire1_01"},{"time":1.7333,"name":"L_fire1_02"},{"time":1.8,"name":"L_fire1_03"},{"time":1.8666,"name":"L_fire1_04"},{"time":1.9333,"name":"L_fire1_05"},{"time":2,"name":"L_fire1_06"}]},"L_fire2_00":{"attachment":[{"time":0,"name":"L_fire2_00"},{"time":0.0666,"name":"L_fire2_01"},{"time":0.1333,"name":"L_fire2_02"},{"time":0.2,"name":"L_fire2_03"},{"time":0.2666,"name":"L_fire2_04"},{"time":0.3333,"name":"L_fire2_05"},{"time":0.4,"name":"L_fire2_06"},{"time":0.4666,"name":"L_fire2_07"},{"time":0.5333,"name":"L_fire2_00"},{"time":0.6,"name":"L_fire2_01"},{"time":0.6666,"name":"L_fire2_02"},{"time":0.7333,"name":"L_fire2_03"},{"time":0.8,"name":"L_fire2_04"},{"time":0.8666,"name":"L_fire2_05"},{"time":0.9333,"name":"L_fire2_06"},{"time":1,"name":"L_fire2_07"},{"time":1.0666,"name":"L_fire2_00"},{"time":1.1333,"name":"L_fire2_01"},{"time":1.2,"name":"L_fire2_02"},{"time":1.2666,"name":"L_fire2_03"},{"time":1.3333,"name":"L_fire2_04"},{"time":1.4,"name":"L_fire2_05"},{"time":1.4666,"name":"L_fire2_06"},{"time":1.5333,"name":"L_fire2_07"},{"time":1.6,"name":"L_fire2_00"},{"time":1.6666,"name":"L_fire2_01"},{"time":1.7333,"name":"L_fire2_02"},{"time":1.8,"name":"L_fire2_03"},{"time":1.8666,"name":"L_fire2_04"},{"time":1.9333,"name":"L_fire2_05"},{"time":2,"name":"L_fire2_06"}]},"MAIN":{"attachment":[{"time":0,"name":"idle_00"},{"time":0.2,"name":"idle_01"},{"time":0.4,"name":"idle_02"},{"time":0.6,"name":"idle_03"},{"time":0.8,"name":"idle_04"},{"time":1,"name":"idle_00"},{"time":1.2,"name":"idle_01"},{"time":1.4,"name":"idle_02"},{"time":1.6,"name":"idle_03"},{"time":1.8,"name":"idle_04"},{"time":2,"name":"idle_00"}]},"R_fire1_00":{"attachment":[{"time":0,"name":"R_fire1_00"},{"time":0.0666,"name":"R_fire1_01"},{"time":0.1333,"name":"R_fire1_02"},{"time":0.2,"name":"R_fire1_03"},{"time":0.2666,"name":"R_fire1_04"},{"time":0.3333,"name":"R_fire1_05"},{"time":0.4,"name":"R_fire1_06"},{"time":0.4666,"name":"R_fire1_07"},{"time":0.5333,"name":"R_fire1_00"},{"time":0.6,"name":"R_fire1_01"},{"time":0.6666,"name":"R_fire1_02"},{"time":0.7333,"name":"R_fire1_03"},{"time":0.8,"name":"R_fire1_04"},{"time":0.8666,"name":"R_fire1_05"},{"time":0.9333,"name":"R_fire1_06"},{"time":1,"name":"R_fire1_07"},{"time":1.0666,"name":"R_fire1_00"},{"time":1.1333,"name":"R_fire1_01"},{"time":1.2,"name":"R_fire1_02"},{"time":1.2666,"name":"R_fire1_03"},{"time":1.3333,"name":"R_fire1_04"},{"time":1.4,"name":"R_fire1_05"},{"time":1.4666,"name":"R_fire1_06"},{"time":1.5333,"name":"R_fire1_07"},{"time":1.6,"name":"R_fire1_00"},{"time":1.6666,"name":"R_fire1_01"},{"time":1.7333,"name":"R_fire1_02"},{"time":1.8,"name":"R_fire1_03"},{"time":1.8666,"name":"R_fire1_04"},{"time":1.9333,"name":"R_fire1_05"},{"time":2,"name":"R_fire1_06"}]},"R_fire2_00":{"attachment":[{"time":0,"name":"R_fire2_00"},{"time":0.0666,"name":"R_fire2_01"},{"time":0.1333,"name":"R_fire2_02"},{"time":0.2,"name":"R_fire2_03"},{"time":0.2666,"name":"R_fire2_04"},{"time":0.3333,"name":"R_fire2_05"},{"time":0.4,"name":"R_fire2_06"},{"time":0.4666,"name":"R_fire2_07"},{"time":0.5333,"name":"R_fire2_00"},{"time":0.6,"name":"R_fire2_01"},{"time":0.6666,"name":"R_fire2_02"},{"time":0.7333,"name":"R_fire2_03"},{"time":0.8,"name":"R_fire2_04"},{"time":0.8666,"name":"R_fire2_05"},{"time":0.9333,"name":"R_fire2_06"},{"time":1,"name":"R_fire2_07"},{"time":1.0666,"name":"R_fire2_00"},{"time":1.1333,"name":"R_fire2_01"},{"time":1.2,"name":"R_fire2_02"},{"time":1.2666,"name":"R_fire2_03"},{"time":1.3333,"name":"R_fire2_04"},{"time":1.4,"name":"R_fire2_05"},{"time":1.4666,"name":"R_fire2_06"},{"time":1.5333,"name":"R_fire2_07"},{"time":1.6,"name":"R_fire2_00"},{"time":1.6666,"name":"R_fire2_01"},{"time":1.7333,"name":"R_fire2_02"},{"time":1.8,"name":"R_fire2_03"},{"time":1.8666,"name":"R_fire2_04"},{"time":1.9333,"name":"R_fire2_05"},{"time":2,"name":"R_fire2_06"}]}},"bones":{"EF1":{"rotate":[{"time":0,"angle":24.76}],"translate":[{"time":0,"x":-510.01,"y":-94.81,"curve":"stepped"},{"time":0.7333,"x":-510.01,"y":-94.81},{"time":1.2666,"x":-564.15,"y":-99.71}],"scale":[{"time":0,"x":0.733,"y":0.733}]},"EF2":{"rotate":[{"time":0.1666,"angle":-118.62}],"translate":[{"time":0.1666,"x":-578.48,"y":-133.89}],"scale":[{"time":0.1666,"x":0.733,"y":0.733}]},"EF3":{"rotate":[{"time":0.3333,"angle":147.72}],"translate":[{"time":0.3333,"x":-680.32,"y":-67.62,"curve":"stepped"},{"time":1.1666,"x":-680.32,"y":-67.62},{"time":1.7,"x":-616.81,"y":-128.08}],"scale":[{"time":0.3333,"x":0.733,"y":0.733}]},"L_arm_2":{"translate":[{"time":0,"x":0,"y":0},{"time":0.6333,"x":0,"y":5.5},{"time":1.0333,"x":0,"y":0},{"time":1.6333,"x":0,"y":7.3},{"time":2,"x":0,"y":0}]},"R_arm_2":{"translate":[{"time":0,"x":0,"y":0},{"time":0.6666,"x":0,"y":5.5},{"time":1.0666,"x":0,"y":0},{"time":1.6666,"x":0,"y":7.3},{"time":2,"x":0,"y":0}]},"R_arm_1":{"translate":[{"time":0,"x":0,"y":0},{"time":0.5666,"x":0,"y":5},{"time":0.9666,"x":0,"y":-1.3},{"time":1.5666,"x":0,"y":5.5},{"time":2,"x":0,"y":0}]},"L_arm_1":{"translate":[{"time":0,"x":0,"y":0},{"time":0.5333,"x":0,"y":5.2},{"time":0.9333,"x":0,"y":-1.09},{"time":1.5333,"x":0,"y":5.7},{"time":2,"x":0,"y":0}]}}}}}