{"skeleton":{"hash":"j2GATgsvcDYX5asy4XqKC9Abh+o","spine":"3.0.12","width":0,"height":0,"images":"./images/"},"bones":[{"name":"root"},{"name":"MAIN","parent":"root","y":70,"color":"ff0004ff"},{"name":"eye","parent":"MAIN","scaleX":2,"scaleY":2,"color":"ff0004ff"},{"name":"dot_slash","parent":"MAIN","y":-3.98,"scaleX":2,"scaleY":2,"color":"23099cff"},{"name":"HITBOX","parent":"MAIN","y":-70,"color":"ff0004ff"},{"name":"EF_main","parent":"root","color":"08ff00ff"},{"name":"EF_wave1_2","parent":"EF_main","x":200,"color":"08ff00ff"},{"name":"EF_wave1_1","parent":"EF_main","x":200,"color":"08ff00ff"},{"name":"EF_water1_2","parent":"EF_main","x":250,"color":"08ff00ff"},{"name":"EF_water1_1","parent":"EF_main","x":250,"color":"08ff00ff"},{"name":"EF_smoke1_2","parent":"EF_main","x":250,"y":50,"color":"08ff00ff"},{"name":"EF_smoke1_1","parent":"EF_main","x":250,"y":50,"color":"08ff00ff"},{"name":"EF_slash3_1","parent":"EF_main","x":250,"y":150,"color":"08ff00ff"},{"name":"EF_slash2_1","parent":"EF_main","x":150,"y":100,"color":"08ff00ff"},{"name":"EF_slash1_1","parent":"EF_main","x":200,"y":50,"color":"08ff00ff"},{"name":"EF_line1_1","parent":"EF_main","x":200,"y":150,"color":"08ff00ff"},{"name":"EF_fire1_2","parent":"EF_main","x":150,"y":50,"color":"08ff00ff"},{"name":"EF_fire1_1","parent":"EF_main","x":150,"y":50,"color":"08ff00ff"},{"name":"EF_eye_ray1_1","parent":"EF_main","x":200,"y":100,"color":"08ff00ff"},{"name":"EF_eye","parent":"EF_main","x":250,"y":100,"color":"08ff00ff"},{"name":"EF_dash1_1","parent":"EF_main","x":150,"color":"08ff00ff"},{"name":"DAMAGEAREA","parent":"root"}],"slots":[{"name":"EF_wave1_1","bone":"EF_wave1_1","blend":"additive"},{"name":"EF_wave1_2","bone":"EF_wave1_2","blend":"additive"},{"name":"EF_fire1_2","bone":"EF_fire1_2","blend":"additive"},{"name":"EF_smoke1_2","bone":"EF_smoke1_2","blend":"additive"},{"name":"EF_line1_1","bone":"EF_line1_1","blend":"additive"},{"name":"MAIN","bone":"MAIN","attachment":"idle_00"},{"name":"dot_slash","bone":"dot_slash","blend":"additive"},{"name":"eye","bone":"eye","blend":"additive"},{"name":"EF_fire1_1","bone":"EF_fire1_1","blend":"additive"},{"name":"EF_slash1_1","bone":"EF_slash1_1","blend":"additive"},{"name":"EF_slash2_1","bone":"EF_slash2_1","blend":"additive"},{"name":"EF_dash1_1","bone":"EF_dash1_1","blend":"additive"},{"name":"EF_smoke1_1","bone":"EF_smoke1_1","blend":"additive"},{"name":"EF_eye_ray1_1","bone":"EF_eye_ray1_1","blend":"additive"},{"name":"EF_water1_1","bone":"EF_water1_1","blend":"additive"},{"name":"EF_water1_2","bone":"EF_water1_2","blend":"additive"},{"name":"EF_eye","bone":"EF_eye","blend":"additive"},{"name":"EF_slash3_1","bone":"EF_slash3_1","blend":"additive"},{"name":"DAMAGEAREA","bone":"DAMAGEAREA"},{"name":"HITBOX","bone":"HITBOX","attachment":"HITBOX"}],"skins":{"default":{"DAMAGEAREA":{"DAMAGEAREA":{"type":"boundingbox","vertices":[-31.85559,-32.01298,31.90206,-32.01298,31.90206,32.02867,-31.85559,32.02867]}},"EF_dash1_1":{"EF/ef_dash_main/ef_dash_main_00001":{"x":30.71,"y":18.11,"width":200,"height":200},"EF/ef_dash_main/ef_dash_main_00002":{"x":30.71,"y":18.11,"width":200,"height":200},"EF/ef_dash_main/ef_dash_main_00003":{"x":30.71,"y":18.11,"width":200,"height":200},"EF/ef_dash_main/ef_dash_main_00004":{"x":30.71,"y":18.11,"width":200,"height":200},"EF/ef_dash_main/ef_dash_main_00005":{"x":30.71,"y":18.11,"width":200,"height":200},"EF/ef_dash_main/ef_dash_main_00006":{"x":30.71,"y":18.11,"width":200,"height":200},"EF/ef_dash_main/ef_dash_main_00007":{"x":30.71,"y":18.11,"width":200,"height":200},"EF/ef_dash_main/ef_dash_main_00008":{"x":30.71,"y":18.11,"width":200,"height":200},"EF/ef_dash_main/ef_dash_main_00009":{"x":30.71,"y":18.11,"width":200,"height":200},"EF/ef_dash_main/ef_dash_main_00010":{"x":30.71,"y":18.11,"width":200,"height":200},"EF/ef_dash_main/ef_dash_main_00011":{"x":30.71,"y":18.11,"width":200,"height":200},"EF/ef_dash_main/ef_dash_main_00012":{"x":30.71,"y":18.11,"width":200,"height":200},"EF/ef_dash_main/ef_dash_main_00013":{"x":30.71,"y":18.11,"width":200,"height":200}},"EF_eye":{"EF/eye_aura/ef_eye_aura_main_00001":{"x":39.38,"y":2.36,"width":180,"height":180},"EF/eye_aura/ef_eye_aura_main_00002":{"x":39.38,"y":2.36,"width":180,"height":180},"EF/eye_aura/ef_eye_aura_main_00003":{"x":39.38,"y":2.36,"width":180,"height":180},"EF/eye_aura/ef_eye_aura_main_00004":{"x":39.38,"y":2.36,"width":180,"height":180},"EF/eye_aura/ef_eye_aura_main_00005":{"x":39.38,"y":2.36,"width":180,"height":180},"EF/eye_aura/ef_eye_aura_main_00006":{"x":39.38,"y":2.36,"width":180,"height":180},"EF/eye_aura/ef_eye_aura_main_00007":{"x":39.38,"y":2.36,"width":180,"height":180},"EF/eye_aura/ef_eye_aura_main_00008":{"x":39.38,"y":2.36,"width":180,"height":180},"EF/eye_aura/ef_eye_aura_main_00009":{"x":39.38,"y":2.36,"width":180,"height":180},"EF/eye_aura/ef_eye_aura_main_00010":{"x":39.38,"y":2.36,"width":180,"height":180},"EF/eye_aura/ef_eye_aura_main_00011":{"x":39.38,"y":2.36,"width":180,"height":180},"EF/eye_aura/ef_eye_aura_main_00012":{"x":39.38,"y":2.36,"width":180,"height":180},"EF/eye_aura/ef_eye_aura_main_00013":{"x":39.38,"y":2.36,"width":180,"height":180},"EF/eye_aura/ef_eye_aura_main_00014":{"x":39.38,"y":2.36,"width":180,"height":180},"EF/eye_aura/ef_eye_aura_main_00015":{"x":39.38,"y":2.36,"width":180,"height":180},"EF/eye_aura/ef_eye_aura_main_00016":{"x":39.38,"y":2.36,"width":180,"height":180},"EF/eye_aura/ef_eye_aura_main_00017":{"x":39.38,"y":2.36,"width":180,"height":180},"EF/eye_aura/ef_eye_aura_main_00018":{"x":39.38,"y":2.36,"width":180,"height":180},"EF/eye_aura/ef_eye_aura_main_00019":{"x":39.38,"y":2.36,"width":180,"height":180},"EF/eye_aura/ef_eye_aura_main_00020":{"x":39.38,"y":2.36,"width":180,"height":180},"EF/eye_aura/ef_eye_aura_main_00021":{"x":39.38,"y":2.36,"width":180,"height":180},"EF/eye_aura/ef_eye_aura_main_00022":{"x":39.38,"y":2.36,"width":180,"height":180},"EF/eye_aura/ef_eye_aura_main_00023":{"x":39.38,"y":2.36,"width":180,"height":180},"EF/eye_aura/ef_eye_aura_main_00024":{"x":39.38,"y":2.36,"width":180,"height":180}},"EF_eye_ray1_1":{"EF/ef_stamp_main/ef_stamp_main_00001":{"width":150,"height":150},"EF/ef_stamp_main/ef_stamp_main_00002":{"width":150,"height":150},"EF/ef_stamp_main/ef_stamp_main_00003":{"width":150,"height":150},"EF/ef_stamp_main/ef_stamp_main_00004":{"width":150,"height":150}},"EF_fire1_1":{"EF/EF_fire/ef_fire_main_00001":{"y":26.62,"width":200,"height":200},"EF/EF_fire/ef_fire_main_00002":{"y":26.62,"width":200,"height":200},"EF/EF_fire/ef_fire_main_00003":{"y":26.62,"width":200,"height":200},"EF/EF_fire/ef_fire_main_00004":{"y":26.62,"width":200,"height":200},"EF/EF_fire/ef_fire_main_00005":{"y":26.62,"width":200,"height":200},"EF/EF_fire/ef_fire_main_00006":{"y":26.62,"width":200,"height":200},"EF/EF_fire/ef_fire_main_00007":{"y":26.62,"width":200,"height":200},"EF/EF_fire/ef_fire_main_00008":{"y":26.62,"width":200,"height":200},"EF/EF_fire/ef_fire_main_00009":{"y":26.62,"width":200,"height":200},"EF/EF_fire/ef_fire_main_00010":{"y":26.62,"width":200,"height":200},"EF/EF_fire/ef_fire_main_00011":{"y":26.62,"width":200,"height":200},"EF/EF_fire/ef_fire_main_00012":{"y":26.62,"width":200,"height":200},"EF/EF_fire/ef_fire_main_00013":{"y":26.62,"width":200,"height":200},"EF/EF_fire/ef_fire_main_00014":{"y":26.62,"width":200,"height":200},"EF/EF_fire/ef_fire_main_00015":{"y":26.62,"width":200,"height":200}},"EF_fire1_2":{"EF/EF_fire/ef_fire_main_00001":{"y":26.62,"width":200,"height":200},"EF/EF_fire/ef_fire_main_00002":{"y":26.62,"width":200,"height":200},"EF/EF_fire/ef_fire_main_00003":{"y":26.62,"width":200,"height":200},"EF/EF_fire/ef_fire_main_00004":{"y":26.62,"width":200,"height":200},"EF/EF_fire/ef_fire_main_00005":{"y":26.62,"width":200,"height":200},"EF/EF_fire/ef_fire_main_00006":{"y":26.62,"width":200,"height":200},"EF/EF_fire/ef_fire_main_00007":{"y":26.62,"width":200,"height":200},"EF/EF_fire/ef_fire_main_00008":{"y":26.62,"width":200,"height":200},"EF/EF_fire/ef_fire_main_00009":{"y":26.62,"width":200,"height":200},"EF/EF_fire/ef_fire_main_00010":{"y":26.62,"width":200,"height":200},"EF/EF_fire/ef_fire_main_00011":{"y":26.62,"width":200,"height":200},"EF/EF_fire/ef_fire_main_00012":{"y":26.62,"width":200,"height":200},"EF/EF_fire/ef_fire_main_00013":{"y":26.62,"width":200,"height":200},"EF/EF_fire/ef_fire_main_00014":{"y":26.62,"width":200,"height":200},"EF/EF_fire/ef_fire_main_00015":{"y":26.62,"width":200,"height":200}},"EF_line1_1":{"EF/ef_slash_line_main 2_00004":{"width":344,"height":80}},"EF_slash1_1":{"EF/EF_slash1_1/ef_slash_A_main_00001":{"width":200,"height":200},"EF/EF_slash1_1/ef_slash_A_main_00002":{"width":200,"height":200},"EF/EF_slash1_1/ef_slash_A_main_00003":{"width":200,"height":200},"EF/EF_slash1_1/ef_slash_A_main_00004":{"width":200,"height":200},"EF/EF_slash1_1/ef_slash_A_main_00005":{"width":200,"height":200},"EF/EF_slash1_1/ef_slash_A_main_00006":{"width":200,"height":200},"EF/EF_slash1_1/ef_slash_A_main_00007":{"width":200,"height":200},"EF/EF_slash1_1/ef_slash_A_main_00008":{"width":200,"height":200},"EF/EF_slash1_1/ef_slash_A_main_00009":{"width":200,"height":200},"EF/EF_slash1_1/ef_slash_A_main_00010":{"width":200,"height":200},"EF/EF_slash1_1/ef_slash_A_main_00011":{"width":200,"height":200},"EF/EF_slash1_1/ef_slash_A_main_00012":{"width":200,"height":200},"EF/EF_slash1_1/ef_slash_A_main_00013":{"width":200,"height":200}},"EF_slash2_1":{"EF/EF_slash2_1/ef_slash_B_main_00001":{"width":200,"height":200},"EF/EF_slash2_1/ef_slash_B_main_00002":{"width":200,"height":200},"EF/EF_slash2_1/ef_slash_B_main_00003":{"width":200,"height":200},"EF/EF_slash2_1/ef_slash_B_main_00004":{"width":200,"height":200},"EF/EF_slash2_1/ef_slash_B_main_00005":{"width":200,"height":200},"EF/EF_slash2_1/ef_slash_B_main_00006":{"width":200,"height":200},"EF/EF_slash2_1/ef_slash_B_main_00007":{"width":200,"height":200},"EF/EF_slash2_1/ef_slash_B_main_00008":{"width":200,"height":200},"EF/EF_slash2_1/ef_slash_B_main_00009":{"width":200,"height":200},"EF/EF_slash2_1/ef_slash_B_main_00010":{"width":200,"height":200},"EF/EF_slash2_1/ef_slash_B_main_00011":{"width":200,"height":200},"EF/EF_slash2_1/ef_slash_B_main_00012":{"width":200,"height":200},"EF/EF_slash2_1/ef_slash_B_main_00013":{"width":200,"height":200},"EF/EF_slash2_1/ef_slash_B_main_00014":{"width":200,"height":200}},"EF_slash3_1":{"EF/ef_slash_C_main/ef_slash_C_main_00001":{"width":200,"height":200},"EF/ef_slash_C_main/ef_slash_C_main_00002":{"width":200,"height":200},"EF/ef_slash_C_main/ef_slash_C_main_00003":{"width":200,"height":200},"EF/ef_slash_C_main/ef_slash_C_main_00004":{"width":200,"height":200},"EF/ef_slash_C_main/ef_slash_C_main_00005":{"width":200,"height":200},"EF/ef_slash_C_main/ef_slash_C_main_00006":{"width":200,"height":200},"EF/ef_slash_C_main/ef_slash_C_main_00007":{"width":200,"height":200},"EF/ef_slash_C_main/ef_slash_C_main_00008":{"width":200,"height":200},"EF/ef_slash_C_main/ef_slash_C_main_00009":{"width":200,"height":200},"EF/ef_slash_C_main/ef_slash_C_main_00010":{"width":200,"height":200},"EF/ef_slash_C_main/ef_slash_C_main_00011":{"width":200,"height":200},"EF/ef_slash_C_main/ef_slash_C_main_00012":{"width":200,"height":200}},"EF_smoke1_1":{"EF/ef_smoke_main/ef_smoke_main_00001":{"y":10.23,"width":200,"height":200},"EF/ef_smoke_main/ef_smoke_main_00002":{"y":10.23,"width":200,"height":200},"EF/ef_smoke_main/ef_smoke_main_00003":{"y":10.23,"width":200,"height":200},"EF/ef_smoke_main/ef_smoke_main_00004":{"y":10.23,"width":200,"height":200},"EF/ef_smoke_main/ef_smoke_main_00005":{"y":10.23,"width":200,"height":200},"EF/ef_smoke_main/ef_smoke_main_00006":{"y":10.23,"width":200,"height":200},"EF/ef_smoke_main/ef_smoke_main_00007":{"y":10.23,"width":200,"height":200},"EF/ef_smoke_main/ef_smoke_main_00008":{"y":10.23,"width":200,"height":200},"EF/ef_smoke_main/ef_smoke_main_00009":{"y":10.23,"width":200,"height":200},"EF/ef_smoke_main/ef_smoke_main_00010":{"y":10.23,"width":200,"height":200},"EF/ef_smoke_main/ef_smoke_main_00011":{"y":10.23,"width":200,"height":200},"EF/ef_smoke_main/ef_smoke_main_00012":{"y":10.23,"width":200,"height":200},"EF/ef_smoke_main/ef_smoke_main_00013":{"y":10.23,"width":200,"height":200},"EF/ef_smoke_main/ef_smoke_main_00014":{"y":10.23,"width":200,"height":200},"EF/ef_smoke_main/ef_smoke_main_00015":{"y":10.23,"width":200,"height":200},"EF/ef_smoke_main/ef_smoke_main_00016":{"y":10.23,"width":200,"height":200}},"EF_smoke1_2":{"EF/ef_smoke_main/ef_smoke_main_00001":{"y":10.23,"width":200,"height":200},"EF/ef_smoke_main/ef_smoke_main_00002":{"y":10.23,"width":200,"height":200},"EF/ef_smoke_main/ef_smoke_main_00003":{"y":10.23,"width":200,"height":200},"EF/ef_smoke_main/ef_smoke_main_00004":{"y":10.23,"width":200,"height":200},"EF/ef_smoke_main/ef_smoke_main_00005":{"y":10.23,"width":200,"height":200},"EF/ef_smoke_main/ef_smoke_main_00006":{"y":10.23,"width":200,"height":200},"EF/ef_smoke_main/ef_smoke_main_00007":{"y":10.23,"width":200,"height":200},"EF/ef_smoke_main/ef_smoke_main_00008":{"y":10.23,"width":200,"height":200},"EF/ef_smoke_main/ef_smoke_main_00009":{"y":10.23,"width":200,"height":200},"EF/ef_smoke_main/ef_smoke_main_00010":{"y":10.23,"width":200,"height":200},"EF/ef_smoke_main/ef_smoke_main_00011":{"y":10.23,"width":200,"height":200},"EF/ef_smoke_main/ef_smoke_main_00012":{"y":10.23,"width":200,"height":200},"EF/ef_smoke_main/ef_smoke_main_00013":{"y":10.23,"width":200,"height":200},"EF/ef_smoke_main/ef_smoke_main_00014":{"y":10.23,"width":200,"height":200},"EF/ef_smoke_main/ef_smoke_main_00015":{"y":10.23,"width":200,"height":200},"EF/ef_smoke_main/ef_smoke_main_00016":{"y":10.23,"width":200,"height":200}},"EF_water1_1":{"EF/ef_tuti_main/ef_tuti_main_00001":{"y":5.51,"width":200,"height":120},"EF/ef_tuti_main/ef_tuti_main_00002":{"y":5.51,"width":200,"height":120},"EF/ef_tuti_main/ef_tuti_main_00003":{"y":5.51,"width":200,"height":120},"EF/ef_tuti_main/ef_tuti_main_00004":{"y":5.51,"width":200,"height":120},"EF/ef_tuti_main/ef_tuti_main_00005":{"y":5.51,"width":200,"height":120},"EF/ef_tuti_main/ef_tuti_main_00006":{"y":5.51,"width":200,"height":120},"EF/ef_tuti_main/ef_tuti_main_00007":{"y":5.51,"width":200,"height":120},"EF/ef_tuti_main/ef_tuti_main_00008":{"y":5.51,"width":200,"height":120},"EF/ef_tuti_main/ef_tuti_main_00009":{"y":5.51,"width":200,"height":120},"EF/ef_tuti_main/ef_tuti_main_00010":{"y":5.51,"width":200,"height":120},"EF/ef_tuti_main/ef_tuti_main_00011":{"y":5.51,"width":200,"height":120},"EF/ef_tuti_main/ef_tuti_main_00012":{"y":5.51,"width":200,"height":120},"EF/ef_tuti_main/ef_tuti_main_00013":{"y":5.51,"width":200,"height":120},"EF/ef_tuti_main/ef_tuti_main_00014":{"y":5.51,"width":200,"height":120},"EF/ef_tuti_main/ef_tuti_main_00015":{"y":5.51,"width":200,"height":120},"EF/ef_tuti_main/ef_tuti_main_00016":{"y":5.51,"width":200,"height":120},"EF/ef_tuti_main/ef_tuti_main_00017":{"y":5.51,"width":200,"height":120}},"EF_water1_2":{"EF/ef_tuti_main/ef_tuti_main_00001":{"y":5.51,"width":200,"height":120},"EF/ef_tuti_main/ef_tuti_main_00002":{"y":5.51,"width":200,"height":120},"EF/ef_tuti_main/ef_tuti_main_00003":{"y":5.51,"width":200,"height":120},"EF/ef_tuti_main/ef_tuti_main_00004":{"y":5.51,"width":200,"height":120},"EF/ef_tuti_main/ef_tuti_main_00005":{"y":5.51,"width":200,"height":120},"EF/ef_tuti_main/ef_tuti_main_00006":{"y":5.51,"width":200,"height":120},"EF/ef_tuti_main/ef_tuti_main_00007":{"y":5.51,"width":200,"height":120},"EF/ef_tuti_main/ef_tuti_main_00008":{"y":5.51,"width":200,"height":120},"EF/ef_tuti_main/ef_tuti_main_00009":{"y":5.51,"width":200,"height":120},"EF/ef_tuti_main/ef_tuti_main_00010":{"y":5.51,"width":200,"height":120},"EF/ef_tuti_main/ef_tuti_main_00011":{"y":5.51,"width":200,"height":120},"EF/ef_tuti_main/ef_tuti_main_00012":{"y":5.51,"width":200,"height":120},"EF/ef_tuti_main/ef_tuti_main_00013":{"y":5.51,"width":200,"height":120},"EF/ef_tuti_main/ef_tuti_main_00014":{"y":5.51,"width":200,"height":120},"EF/ef_tuti_main/ef_tuti_main_00015":{"y":5.51,"width":200,"height":120},"EF/ef_tuti_main/ef_tuti_main_00016":{"y":5.51,"width":200,"height":120},"EF/ef_tuti_main/ef_tuti_main_00017":{"y":5.51,"width":200,"height":120}},"EF_wave1_1":{"EF/ef_graund_wave_main/ef_graund_wave_main_00001":{"y":13.52,"width":280,"height":168},"EF/ef_graund_wave_main/ef_graund_wave_main_00002":{"y":13.52,"width":280,"height":168},"EF/ef_graund_wave_main/ef_graund_wave_main_00003":{"y":13.52,"width":280,"height":168},"EF/ef_graund_wave_main/ef_graund_wave_main_00004":{"y":13.52,"width":280,"height":168},"EF/ef_graund_wave_main/ef_graund_wave_main_00005":{"y":13.52,"width":280,"height":168},"EF/ef_graund_wave_main/ef_graund_wave_main_00006":{"y":13.52,"width":280,"height":168},"EF/ef_graund_wave_main/ef_graund_wave_main_00007":{"y":13.52,"width":280,"height":168},"EF/ef_graund_wave_main/ef_graund_wave_main_00008":{"y":13.52,"width":280,"height":168},"EF/ef_graund_wave_main/ef_graund_wave_main_00009":{"y":13.52,"width":280,"height":168},"EF/ef_graund_wave_main/ef_graund_wave_main_00010":{"y":13.52,"width":280,"height":168},"EF/ef_graund_wave_main/ef_graund_wave_main_00011":{"y":13.52,"width":280,"height":168},"EF/ef_graund_wave_main/ef_graund_wave_main_00012":{"y":13.52,"width":280,"height":168},"EF/ef_graund_wave_main/ef_graund_wave_main_00013":{"y":13.52,"width":280,"height":168},"EF/ef_graund_wave_main/ef_graund_wave_main_00014":{"y":13.52,"width":280,"height":168}},"EF_wave1_2":{"EF/ef_graund_wave_main/ef_graund_wave_main_00001":{"y":13.52,"width":280,"height":168},"EF/ef_graund_wave_main/ef_graund_wave_main_00002":{"y":13.52,"width":280,"height":168},"EF/ef_graund_wave_main/ef_graund_wave_main_00003":{"y":13.52,"width":280,"height":168},"EF/ef_graund_wave_main/ef_graund_wave_main_00004":{"y":13.52,"width":280,"height":168},"EF/ef_graund_wave_main/ef_graund_wave_main_00005":{"y":13.52,"width":280,"height":168},"EF/ef_graund_wave_main/ef_graund_wave_main_00006":{"y":13.52,"width":280,"height":168},"EF/ef_graund_wave_main/ef_graund_wave_main_00007":{"y":13.52,"width":280,"height":168},"EF/ef_graund_wave_main/ef_graund_wave_main_00008":{"y":13.52,"width":280,"height":168},"EF/ef_graund_wave_main/ef_graund_wave_main_00009":{"y":13.52,"width":280,"height":168},"EF/ef_graund_wave_main/ef_graund_wave_main_00010":{"y":13.52,"width":280,"height":168},"EF/ef_graund_wave_main/ef_graund_wave_main_00011":{"y":13.52,"width":280,"height":168},"EF/ef_graund_wave_main/ef_graund_wave_main_00012":{"y":13.52,"width":280,"height":168},"EF/ef_graund_wave_main/ef_graund_wave_main_00013":{"y":13.52,"width":280,"height":168},"EF/ef_graund_wave_main/ef_graund_wave_main_00014":{"y":13.52,"width":280,"height":168}},"HITBOX":{"HITBOX":{"type":"boundingbox","vertices":[-23.36998,0.28821,23.36999,0.28821,23.36999,118.98319,-23.36998,118.98319]}},"MAIN":{"attack1_00":{"y":-3.97,"scaleX":2,"scaleY":2,"width":256,"height":256},"attack1_01":{"y":-3.97,"scaleX":2,"scaleY":2,"width":256,"height":256},"attack1_02":{"y":-3.97,"scaleX":2,"scaleY":2,"width":256,"height":256},"attack1_03":{"y":-3.97,"scaleX":2,"scaleY":2,"width":256,"height":256},"attack1_04":{"y":-3.97,"scaleX":2,"scaleY":2,"width":256,"height":256},"attack1_05":{"y":-3.97,"scaleX":2,"scaleY":2,"width":256,"height":256},"attack1_06":{"y":-3.97,"scaleX":2,"scaleY":2,"width":256,"height":256},"attack1_07":{"y":-3.97,"scaleX":2,"scaleY":2,"width":256,"height":256},"attack1_08":{"y":-3.97,"scaleX":2,"scaleY":2,"width":256,"height":256},"attack1_09":{"y":-3.97,"scaleX":2,"scaleY":2,"width":256,"height":256},"attack1_10":{"y":-3.97,"scaleX":2,"scaleY":2,"width":256,"height":256},"attack1_11":{"y":-3.97,"scaleX":2,"scaleY":2,"width":256,"height":256},"attack1_12":{"y":-3.97,"scaleX":2,"scaleY":2,"width":256,"height":256},"attack1_13":{"y":-3.97,"scaleX":2,"scaleY":2,"width":256,"height":256},"attack1_14":{"y":-3.97,"scaleX":2,"scaleY":2,"width":256,"height":256},"back_00":{"y":-3.97,"scaleX":2,"scaleY":2,"width":256,"height":256},"damage_00":{"y":-3.97,"scaleX":2,"scaleY":2,"width":256,"height":256},"front_00":{"y":-3.97,"scaleX":2,"scaleY":2,"width":256,"height":256},"idle_00":{"y":-3.97,"scaleX":2,"scaleY":2,"width":256,"height":256},"idle_01":{"y":-3.97,"scaleX":2,"scaleY":2,"width":256,"height":256},"idle_02":{"y":-3.97,"scaleX":2,"scaleY":2,"width":256,"height":256},"idle_03":{"y":-3.97,"scaleX":2,"scaleY":2,"width":256,"height":256},"in_00":{"y":-3.8,"scaleX":2,"scaleY":2,"width":256,"height":256},"in_01":{"y":-3.8,"scaleX":2,"scaleY":2,"width":256,"height":256},"skill1_00":{"y":-3.97,"scaleX":2,"scaleY":2,"width":256,"height":256},"skill1_01":{"y":-3.97,"scaleX":2,"scaleY":2,"width":256,"height":256},"skill1_02":{"y":-3.97,"scaleX":2,"scaleY":2,"width":256,"height":256},"skill1_03":{"y":-3.97,"scaleX":2,"scaleY":2,"width":256,"height":256},"skill1_04":{"y":-3.97,"scaleX":2,"scaleY":2,"width":256,"height":256},"skill1_05":{"y":-3.97,"scaleX":2,"scaleY":2,"width":256,"height":256},"skill1_06":{"y":-3.97,"scaleX":2,"scaleY":2,"width":256,"height":256},"skill1_07":{"y":-3.97,"scaleX":2,"scaleY":2,"width":256,"height":256},"skill1_08":{"y":-3.97,"scaleX":2,"scaleY":2,"width":256,"height":256},"skill1_09":{"y":-3.97,"scaleX":2,"scaleY":2,"width":256,"height":256},"skill1_10":{"y":-3.97,"scaleX":2,"scaleY":2,"width":256,"height":256},"skill1_11":{"y":-3.97,"scaleX":2,"scaleY":2,"width":256,"height":256},"skill1_12":{"y":-3.97,"scaleX":2,"scaleY":2,"width":256,"height":256},"skill2_00":{"y":-3.97,"scaleX":2,"scaleY":2,"width":256,"height":256},"skill2_01":{"y":-3.97,"scaleX":2,"scaleY":2,"width":256,"height":256},"skill2_02":{"y":-3.97,"scaleX":2,"scaleY":2,"width":256,"height":256},"skill2_03":{"y":-3.97,"scaleX":2,"scaleY":2,"width":256,"height":256},"skill2_04":{"y":-3.97,"scaleX":2,"scaleY":2,"width":256,"height":256},"skill2_05":{"y":-3.97,"scaleX":2,"scaleY":2,"width":256,"height":256},"skill2_06":{"y":-3.97,"scaleX":2,"scaleY":2,"width":256,"height":256},"skill2_07":{"y":-3.97,"scaleX":2,"scaleY":2,"width":256,"height":256},"skill2_08":{"y":-3.97,"scaleX":2,"scaleY":2,"width":256,"height":256},"skill2_09":{"y":-3.97,"scaleX":2,"scaleY":2,"width":256,"height":256},"skill2_10":{"y":-3.97,"scaleX":2,"scaleY":2,"width":256,"height":256},"skill2_11":{"y":-3.97,"scaleX":2,"scaleY":2,"width":256,"height":256},"skill3_00":{"y":-3.97,"scaleX":2,"scaleY":2,"width":256,"height":256},"skill3_01":{"y":-3.97,"scaleX":2,"scaleY":2,"width":256,"height":256},"skill3_02":{"y":-3.97,"scaleX":2,"scaleY":2,"width":256,"height":256},"skill3_03":{"y":-3.97,"scaleX":2,"scaleY":2,"width":256,"height":256},"skill3_04":{"y":-3.97,"scaleX":2,"scaleY":2,"width":256,"height":256},"skill3_05":{"y":-3.97,"scaleX":2,"scaleY":2,"width":256,"height":256},"skill3_06":{"y":-3.97,"scaleX":2,"scaleY":2,"width":256,"height":256}},"dot_slash":{"EF/dot_slash/EF_attack1_02":{"width":256,"height":256},"EF/dot_slash/EF_attack1_03":{"width":256,"height":256},"EF/dot_slash/EF_attack1_04":{"width":256,"height":256},"EF/dot_slash/EF_attack1_05":{"width":256,"height":256},"EF/dot_slash/EF_attack1_06":{"width":256,"height":256},"EF/dot_slash/EF_attack1_07":{"width":256,"height":256},"EF/dot_slash/EF_attack1_08":{"width":256,"height":256},"EF/dot_slash/EF_attack1_09":{"width":256,"height":256},"EF/dot_slash/EF_attack1_10":{"width":256,"height":256}},"eye":{"EF/eye_EF/eye_attack1_00":{"width":256,"height":256},"EF/eye_EF/eye_attack1_01":{"width":256,"height":256},"EF/eye_EF/eye_attack1_02":{"width":256,"height":256},"EF/eye_EF/eye_attack1_03":{"width":256,"height":256},"EF/eye_EF/eye_attack1_04":{"width":256,"height":256},"EF/eye_EF/eye_attack1_05":{"width":256,"height":256},"EF/eye_EF/eye_attack1_06":{"width":256,"height":256},"EF/eye_EF/eye_attack1_07":{"width":256,"height":256},"EF/eye_EF/eye_attack1_08":{"width":256,"height":256},"EF/eye_EF/eye_attack1_15":{"width":256,"height":256},"EF/eye_EF/eye_attack1_16":{"width":256,"height":256},"EF/eye_EF/eye_skill1_06":{"width":256,"height":256},"EF/eye_EF/eye_skill1_07":{"width":256,"height":256},"EF/eye_EF/eye_skill1_12":{"width":256,"height":256},"EF/eye_EF/eye_skill2_01":{"width":256,"height":256},"EF/eye_EF/eye_skill2_02":{"width":256,"height":256},"EF/eye_EF/eye_skill2_03":{"width":256,"height":256},"EF/eye_EF/eye_skill2_04":{"width":256,"height":256},"EF/eye_EF/eye_skill2_05":{"width":256,"height":256},"EF/eye_EF/eye_skill2_06":{"width":256,"height":256},"EF/eye_EF/eye_skill2_07":{"width":256,"height":256},"EF/eye_EF/eye_skill2_08":{"width":256,"height":256},"EF/eye_EF/eye_skill2_09":{"width":256,"height":256},"EF/eye_EF/eye_skill2_10":{"width":256,"height":256},"EF/eye_EF/eye_skill2_03_2":{"width":256,"height":256},"EF/eye_EF/eye_skill2_03_3":{"width":256,"height":256},"EF/eye_EF/eye_skill3_00":{"width":256,"height":256},"EF/eye_EF/eye_skill3_01":{"width":256,"height":256},"EF/eye_EF/eye_skill3_02":{"width":256,"height":256},"EF/eye_EF/eye_skill3_03":{"width":256,"height":256},"EF/eye_EF/eye_skill3_04":{"width":256,"height":256},"EF/eye_EF/eye_skill3_05":{"width":256,"height":256},"EF/eye_EF/eye_skill3_06":{"width":256,"height":256},"EF/eye_EF/eye_skill3_08":{"width":256,"height":256},"EF/eye_EF/eye_skill3_05_2":{"width":256,"height":256}}}},"events":{"Event":{},"Event2":{},"Hit":{},"Sound1":{},"Sound2":{},"Sound3":{},"Voice":{}},"animations":{"attack1":{"slots":{"DAMAGEAREA":{"attachment":[{"time":0.2333,"name":"DAMAGEAREA"},{"time":0.2666,"name":null},{"time":0.8,"name":"DAMAGEAREA"},{"time":0.8333,"name":null}]},"MAIN":{"attachment":[{"time":0,"name":"attack1_00"},{"time":0.0333,"name":"attack1_00"},{"time":0.0666,"name":"attack1_01"},{"time":0.2,"name":"attack1_02"},{"time":0.2333,"name":"attack1_03"},{"time":0.2666,"name":"attack1_04"},{"time":0.4,"name":"attack1_05"},{"time":0.4666,"name":"attack1_06"},{"time":0.5666,"name":"attack1_07"},{"time":0.7,"name":"attack1_08"},{"time":0.8,"name":"attack1_09"},{"time":0.8666,"name":"attack1_10"},{"time":1.1333,"name":"attack1_11"},{"time":1.1666,"name":"skill1_06"},{"time":1.4333,"name":"attack1_12"},{"time":1.6666,"name":"idle_00"}]},"dot_slash":{"attachment":[{"time":0.2,"name":"EF/dot_slash/EF_attack1_02"},{"time":0.2333,"name":"EF/dot_slash/EF_attack1_03"},{"time":0.2666,"name":"EF/dot_slash/EF_attack1_04"},{"time":0.4,"name":"EF/dot_slash/EF_attack1_05"},{"time":0.4666,"name":"EF/dot_slash/EF_attack1_06"},{"time":0.5666,"name":"EF/dot_slash/EF_attack1_07"},{"time":0.7,"name":"EF/dot_slash/EF_attack1_08"},{"time":0.8,"name":"EF/dot_slash/EF_attack1_09"},{"time":0.8333,"name":"EF/dot_slash/EF_attack1_10"},{"time":0.8666,"name":null}]}},"bones":{"MAIN":{"translate":[{"time":0,"x":-17.09,"y":0},{"time":0.0666,"x":-34.19,"y":0,"curve":"stepped"},{"time":0.1666,"x":-34.19,"y":0,"curve":"stepped"},{"time":0.2,"x":-83.52,"y":4.4,"curve":"stepped"},{"time":0.2333,"x":-131.82,"y":-4.13,"curve":[0.131,0.43,0.75,1]},{"time":0.4,"x":-150.92,"y":-4.13,"curve":"stepped"},{"time":0.4666,"x":-150.92,"y":-4.13,"curve":"stepped"},{"time":0.5666,"x":-168.36,"y":-4.07,"curve":"stepped"},{"time":0.7,"x":-181.23,"y":-6.82,"curve":"stepped"},{"time":0.8,"x":-215.74,"y":0,"curve":"stepped"},{"time":1.1333,"x":-209.69,"y":0,"curve":"stepped"},{"time":1.1666,"x":-143.21,"y":11.35,"curve":[0.348,0.84,0.545,0.92]},{"time":1.3333,"x":-51.14,"y":13.38},{"time":1.4333,"x":-26.2,"y":-0.51,"curve":[0.276,0.52,0.75,1]},{"time":1.6,"x":-19.34,"y":0,"curve":"stepped"},{"time":1.6666,"x":0,"y":0.51}]},"dot_slash":{"translate":[{"time":0.2,"x":0,"y":0,"curve":"stepped"},{"time":0.2333,"x":-31.55,"y":-13.72,"curve":"stepped"},{"time":0.2666,"x":0,"y":0,"curve":"stepped"},{"time":0.8,"x":10.97,"y":37.04}],"scale":[{"time":0.2333,"x":1.497,"y":1.497,"curve":"stepped"},{"time":0.2666,"x":1,"y":1,"curve":"stepped"},{"time":0.8,"x":1.497,"y":1.497}]},"DAMAGEAREA":{"translate":[{"time":0.2333,"x":-235.41,"y":63.19,"curve":"stepped"},{"time":0.8,"x":-274.91,"y":64.78}],"scale":[{"time":0.2333,"x":3.685,"y":2.548,"curve":"stepped"},{"time":0.8,"x":2.54,"y":2.964}]}},"events":[{"time":0.0333,"name":"Event","float":0.15,"string":"kHitStopType_normal"},{"time":0.2,"name":"Sound1","string":"cri_se_battle_monster_swish"},{"time":0.2,"name":"Sound3","string":"setHitSound(se_battle_019_sword_hit_03)"},{"time":0.2,"name":"Voice","string":"cri_718_voice_attack_random"},{"time":0.6666,"name":"Sound1","string":"cri_se_battle_monster_swish"},{"time":0.6666,"name":"Voice","string":"cri_718_voice_attack_c"},{"time":0.8,"name":"Hit","string":"resetHitList"},{"time":1.1666,"name":"Sound1","string":"cri_se_battle_jump"},{"time":1.4333,"name":"Sound1","string":"cri_se_battle_landing"}]},"back":{"slots":{"MAIN":{"attachment":[{"time":0,"name":"idle_00"},{"time":0.0333,"name":"skill1_06"},{"time":0.4333,"name":"attack1_12"},{"time":0.6666,"name":"idle_00"}]}},"bones":{"MAIN":{"translate":[{"time":0,"x":0,"y":11.35,"curve":[0.348,0.84,0.545,0.92]},{"time":0.1666,"x":120.01,"y":13.38},{"time":0.4333,"x":135,"y":-0.51,"curve":[0.276,0.52,0.75,1]},{"time":0.6,"x":139,"y":0,"curve":"stepped"},{"time":0.6666,"x":140,"y":0.51}]}}},"cast":{"slots":{"MAIN":{"attachment":[{"time":0,"name":"attack1_00"},{"time":0.0333,"name":"attack1_00"},{"time":0.0666,"name":"attack1_01"},{"time":0.4666,"name":"attack1_02"},{"time":0.5,"name":"attack1_03"},{"time":0.5333,"name":"attack1_04"},{"time":0.8666,"name":"attack1_05"},{"time":1,"name":"idle_00"}]}},"bones":{"MAIN":{"translate":[{"time":0,"x":-17.09,"y":0}]}},"events":[{"time":0.4666,"name":"Voice","string":"cri_718_voice_item"}]},"damage":{"slots":{"MAIN":{"attachment":[{"time":0,"name":"damage_00"}]}}},"front":{"slots":{"MAIN":{"attachment":[{"time":0,"name":"front_00"}]}}},"idle":{"slots":{"MAIN":{"attachment":[{"time":0,"name":"idle_00"},{"time":0.2333,"name":"idle_01"},{"time":0.5,"name":"idle_02"},{"time":0.7666,"name":"idle_03"},{"time":1,"name":"idle_00"}]}}},"in":{"slots":{"MAIN":{"attachment":[{"time":0,"name":"in_00"},{"time":0.3666,"name":"in_01"},{"time":0.5333,"name":"skill2_02"},{"time":0.6,"name":"skill2_01"},{"time":0.7,"name":"skill2_00"},{"time":0.8,"name":"attack1_13"},{"time":0.9,"name":"attack1_14"},{"time":1,"name":"idle_00"}]}},"bones":{"MAIN":{"translate":[{"time":0,"x":-19.82,"y":0,"curve":"stepped"},{"time":0.0333,"x":-19.82,"y":-3.96,"curve":"stepped"},{"time":0.0666,"x":-19.82,"y":0,"curve":"stepped"},{"time":0.3666,"x":-11.89,"y":0,"curve":"stepped"},{"time":0.5333,"x":16.52,"y":0,"curve":"stepped"},{"time":0.6,"x":16.52,"y":0,"curve":"stepped"},{"time":0.7,"x":16.52,"y":0,"curve":"stepped"},{"time":0.8,"x":0,"y":0,"curve":"stepped"},{"time":1,"x":0,"y":0}]}},"events":[{"time":0.3666,"name":"Sound1","string":"cri_se_battle_sword_draw_01"},{"time":0.6666,"name":"Event","string":"takeBattleEffectAnimation(summon_3)"}]},"skill1":{"slots":{"DAMAGEAREA":{"attachment":[{"time":1.8333,"name":"DAMAGEAREA"},{"time":1.9333,"name":null}]},"EF_dash1_1":{"attachment":[{"time":0.2666,"name":"EF/ef_dash_main/ef_dash_main_00001"},{"time":0.3,"name":"EF/ef_dash_main/ef_dash_main_00002"},{"time":0.3333,"name":"EF/ef_dash_main/ef_dash_main_00004"},{"time":0.3666,"name":"EF/ef_dash_main/ef_dash_main_00005"},{"time":0.4,"name":"EF/ef_dash_main/ef_dash_main_00006"},{"time":0.4333,"name":"EF/ef_dash_main/ef_dash_main_00007"},{"time":0.4666,"name":"EF/ef_dash_main/ef_dash_main_00008"},{"time":0.5,"name":"EF/ef_dash_main/ef_dash_main_00009"},{"time":0.5333,"name":"EF/ef_dash_main/ef_dash_main_00010"},{"time":0.5666,"name":"EF/ef_dash_main/ef_dash_main_00011"},{"time":0.6,"name":"EF/ef_dash_main/ef_dash_main_00012"},{"time":0.6333,"name":"EF/ef_dash_main/ef_dash_main_00013"},{"time":0.6666,"name":null},{"time":1.5666,"name":"EF/ef_dash_main/ef_dash_main_00001"},{"time":1.6,"name":"EF/ef_dash_main/ef_dash_main_00002"},{"time":1.6333,"name":"EF/ef_dash_main/ef_dash_main_00004"},{"time":1.6666,"name":"EF/ef_dash_main/ef_dash_main_00005"},{"time":1.7,"name":"EF/ef_dash_main/ef_dash_main_00006"},{"time":1.7333,"name":"EF/ef_dash_main/ef_dash_main_00007"},{"time":1.7666,"name":"EF/ef_dash_main/ef_dash_main_00008"},{"time":1.8,"name":"EF/ef_dash_main/ef_dash_main_00009"},{"time":1.8333,"name":"EF/ef_dash_main/ef_dash_main_00010"},{"time":1.8666,"name":"EF/ef_dash_main/ef_dash_main_00011"},{"time":1.9,"name":"EF/ef_dash_main/ef_dash_main_00012"},{"time":1.9333,"name":"EF/ef_dash_main/ef_dash_main_00013"},{"time":1.9666,"name":null}]},"EF_slash3_1":{"attachment":[{"time":1.8,"name":"EF/ef_slash_C_main/ef_slash_C_main_00001"},{"time":1.8333,"name":"EF/ef_slash_C_main/ef_slash_C_main_00002"},{"time":1.8666,"name":"EF/ef_slash_C_main/ef_slash_C_main_00003"},{"time":1.9,"name":"EF/ef_slash_C_main/ef_slash_C_main_00004"},{"time":1.9333,"name":"EF/ef_slash_C_main/ef_slash_C_main_00005"},{"time":1.9666,"name":"EF/ef_slash_C_main/ef_slash_C_main_00006"},{"time":2,"name":"EF/ef_slash_C_main/ef_slash_C_main_00007"},{"time":2.0333,"name":"EF/ef_slash_C_main/ef_slash_C_main_00008"},{"time":2.0666,"name":"EF/ef_slash_C_main/ef_slash_C_main_00009"},{"time":2.1,"name":"EF/ef_slash_C_main/ef_slash_C_main_00010"},{"time":2.1333,"name":"EF/ef_slash_C_main/ef_slash_C_main_00011"},{"time":2.1666,"name":"EF/ef_slash_C_main/ef_slash_C_main_00012"},{"time":2.2,"name":null}]},"EF_wave1_1":{"attachment":[{"time":0.2666,"name":"EF/ef_graund_wave_main/ef_graund_wave_main_00001"},{"time":0.3,"name":"EF/ef_graund_wave_main/ef_graund_wave_main_00003"},{"time":0.3333,"name":"EF/ef_graund_wave_main/ef_graund_wave_main_00005"},{"time":0.3666,"name":"EF/ef_graund_wave_main/ef_graund_wave_main_00007"},{"time":0.4,"name":"EF/ef_graund_wave_main/ef_graund_wave_main_00009"},{"time":0.4333,"name":"EF/ef_graund_wave_main/ef_graund_wave_main_00011"},{"time":0.4666,"name":"EF/ef_graund_wave_main/ef_graund_wave_main_00013"},{"time":0.5,"name":"EF/ef_graund_wave_main/ef_graund_wave_main_00014"},{"time":0.5333,"name":null},{"time":1,"name":"EF/ef_graund_wave_main/ef_graund_wave_main_00001"},{"time":1.0333,"name":"EF/ef_graund_wave_main/ef_graund_wave_main_00004"},{"time":1.0666,"name":"EF/ef_graund_wave_main/ef_graund_wave_main_00005"},{"time":1.1,"name":"EF/ef_graund_wave_main/ef_graund_wave_main_00006"},{"time":1.1333,"name":"EF/ef_graund_wave_main/ef_graund_wave_main_00007"},{"time":1.1666,"name":"EF/ef_graund_wave_main/ef_graund_wave_main_00008"},{"time":1.2,"name":"EF/ef_graund_wave_main/ef_graund_wave_main_00009"},{"time":1.2333,"name":"EF/ef_graund_wave_main/ef_graund_wave_main_00010"},{"time":1.2666,"name":"EF/ef_graund_wave_main/ef_graund_wave_main_00011"},{"time":1.3,"name":"EF/ef_graund_wave_main/ef_graund_wave_main_00012"},{"time":1.3333,"name":"EF/ef_graund_wave_main/ef_graund_wave_main_00013"},{"time":1.3666,"name":"EF/ef_graund_wave_main/ef_graund_wave_main_00014"},{"time":1.4,"name":null},{"time":1.5666,"name":"EF/ef_graund_wave_main/ef_graund_wave_main_00001"},{"time":1.6,"name":"EF/ef_graund_wave_main/ef_graund_wave_main_00003"},{"time":1.6333,"name":"EF/ef_graund_wave_main/ef_graund_wave_main_00005"},{"time":1.6666,"name":"EF/ef_graund_wave_main/ef_graund_wave_main_00007"},{"time":1.7,"name":"EF/ef_graund_wave_main/ef_graund_wave_main_00009"},{"time":1.7333,"name":"EF/ef_graund_wave_main/ef_graund_wave_main_00011"},{"time":1.7666,"name":"EF/ef_graund_wave_main/ef_graund_wave_main_00013"},{"time":1.8,"name":"EF/ef_graund_wave_main/ef_graund_wave_main_00014"},{"time":1.8333,"name":null}]},"EF_wave1_2":{"attachment":[{"time":1.8333,"name":"EF/ef_graund_wave_main/ef_graund_wave_main_00001"},{"time":1.8666,"name":"EF/ef_graund_wave_main/ef_graund_wave_main_00002"},{"time":1.9,"name":"EF/ef_graund_wave_main/ef_graund_wave_main_00003"},{"time":1.9333,"name":"EF/ef_graund_wave_main/ef_graund_wave_main_00004"},{"time":1.9666,"name":"EF/ef_graund_wave_main/ef_graund_wave_main_00005"},{"time":2,"name":"EF/ef_graund_wave_main/ef_graund_wave_main_00006"},{"time":2.0333,"name":"EF/ef_graund_wave_main/ef_graund_wave_main_00007"},{"time":2.0666,"name":"EF/ef_graund_wave_main/ef_graund_wave_main_00008"},{"time":2.1,"name":"EF/ef_graund_wave_main/ef_graund_wave_main_00009"},{"time":2.1333,"name":"EF/ef_graund_wave_main/ef_graund_wave_main_00010"},{"time":2.1666,"name":"EF/ef_graund_wave_main/ef_graund_wave_main_00011"},{"time":2.2,"name":"EF/ef_graund_wave_main/ef_graund_wave_main_00012"},{"time":2.2333,"name":"EF/ef_graund_wave_main/ef_graund_wave_main_00013"},{"time":2.2666,"name":"EF/ef_graund_wave_main/ef_graund_wave_main_00014"},{"time":2.3,"name":null}]},"MAIN":{"attachment":[{"time":0,"name":"attack1_00"},{"time":0.0333,"name":"attack1_01"},{"time":0.1666,"name":"skill1_00"},{"time":0.2666,"name":"skill1_02"},{"time":0.7666,"name":"skill1_03"},{"time":0.8666,"name":"skill1_04"},{"time":1,"name":"skill1_05"},{"time":1.0333,"name":"skill1_06"},{"time":1.2333,"name":"skill1_07"},{"time":1.4666,"name":"skill1_08"},{"time":1.5666,"name":"skill1_09"},{"time":1.6666,"name":"skill1_10"},{"time":1.8333,"name":"attack1_09"},{"time":2.1666,"name":"attack1_10"},{"time":2.2333,"name":"skill1_06"},{"time":2.4666,"name":"attack1_12"},{"time":2.7,"name":"attack1_14"},{"time":2.8333,"name":"idle_00"}],"color":[{"time":0.2666,"color":"ffffffff"},{"time":0.3666,"color":"ffffff00","curve":"stepped"},{"time":0.6666,"color":"ffffff00"},{"time":0.7666,"color":"ffffffff"}]}},"bones":{"MAIN":{"translate":[{"time":0.2333,"x":1.09,"y":1.09},{"time":0.2666,"x":-60.41,"y":11.45,"curve":[0.195,0.71,0.75,1]},{"time":0.3666,"x":-247.9,"y":11.45,"curve":"stepped"},{"time":0.6666,"x":292.76,"y":7.82,"curve":[0.19,0.49,0.75,1]},{"time":0.7666,"x":94.55,"y":7.82,"curve":"stepped"},{"time":0.8666,"x":49.92,"y":11.45,"curve":"stepped"},{"time":1,"x":101.06,"y":3.72,"curve":[0.104,0.46,0.558,0.8]},{"time":1.1333,"x":179.7,"y":10.82},{"time":1.2333,"x":222.35,"y":0,"curve":[0.164,0.79,0.392,0.93]},{"time":1.4,"x":258.51,"y":0},{"time":1.5,"x":261.29,"y":0},{"time":1.5333,"x":262.7,"y":-4.23},{"time":1.5666,"x":225.39,"y":46.54,"curve":[0.071,0.76,0.317,0.95]},{"time":1.8,"x":78.07,"y":217.15,"curve":"stepped"},{"time":1.8333,"x":42.44,"y":1.41,"curve":"stepped"},{"time":2.2333,"x":118.92,"y":8.81},{"time":2.3666,"x":256.67,"y":17.63},{"time":2.4666,"x":326.1,"y":0,"curve":[0.07,0.27,0.75,1]},{"time":2.6333,"x":343.52,"y":0,"curve":"stepped"},{"time":2.7,"x":364.15,"y":0},{"time":2.8333,"x":373.03,"y":0}]},"eye":{"translate":[{"time":0.2333,"x":60.41,"y":-11.45},{"time":0.3,"x":82.28,"y":-11.45},{"time":0.3666,"x":269.77,"y":-11.45,"curve":"stepped"},{"time":0.6666,"x":-270.88,"y":-11.45}]},"dot_slash":{"translate":[{"time":0.2333,"x":60.41,"y":-11.45},{"time":0.3,"x":82.28,"y":-11.45},{"time":0.3666,"x":269.77,"y":-11.45}]},"EF_wave1_1":{"translate":[{"time":0.2666,"x":-200,"y":0,"curve":"stepped"},{"time":1,"x":-110.97,"y":11.88,"curve":"stepped"},{"time":1.5666,"x":31.17,"y":0}],"scale":[{"time":0.2666,"x":1.5,"y":1.5}]},"EF_dash1_1":{"translate":[{"time":0.2666,"x":-136.06,"y":0,"curve":"stepped"},{"time":1.5666,"x":113.6,"y":0}],"scale":[{"time":0.2666,"x":1.5,"y":1.5,"curve":"stepped"},{"time":1.5666,"x":1.5,"y":1.5}]},"EF_slash3_1":{"translate":[{"time":1.8,"x":-196.31,"y":37.8}],"scale":[{"time":1.8,"x":3.225,"y":3.225}]},"EF_wave1_2":{"translate":[{"time":1.8333,"x":-146.32,"y":0}],"scale":[{"time":1.8333,"x":3,"y":3}]},"DAMAGEAREA":{"translate":[{"time":1.8333,"x":-23.7,"y":120.07}],"scale":[{"time":1.8333,"x":3.275,"y":5.241}]}},"events":[{"time":0,"name":"Event","string":"runScript-setMainDamage"},{"time":0.1666,"name":"Event","string":"runScript-addShot"},{"time":0.1666,"name":"Sound1","string":"cri_se_battle_skill_shot"},{"time":0.1666,"name":"Sound2","string":"cri_se_battle_monster_swish"},{"time":0.1666,"name":"Sound3","string":"setHitSound(se_battle_swordslash_heavy)"},{"time":0.2666,"name":"Event","float":-1,"string":"addOrbitSystem_hit"},{"time":0.6666,"name":"Event","string":"setPosition_Target"},{"time":0.8,"name":"Sound1","string":"cri_se_battle_landing"},{"time":0.9666,"name":"Sound1","string":"cri_se_battle_jump"},{"time":0.9666,"name":"Sound2","string":"cri_se_battle_monster_swish"},{"time":1.2333,"name":"Sound1","string":"cri_se_battle_landing"},{"time":1.5666,"name":"Sound1","string":"cri_se_battle_jump"},{"time":1.5666,"name":"Sound2","string":"cri_se_battle_skill_shot"},{"time":1.6666,"name":"Voice","string":"cri_718_voice_skill_all"},{"time":1.8,"name":"Event","float":0.3,"string":"kHitStopType_normal"},{"time":1.8,"name":"Sound1","string":"cri_se_battle_skill_swish"},{"time":1.8,"name":"Sound2","string":"cri_se_battle_037_explosion_element_05"},{"time":1.8333,"name":"Event","float":1,"string":"shakeGround"},{"time":2.2333,"name":"Sound1","string":"cri_se_battle_jump"},{"time":2.4666,"name":"Sound1","string":"cri_se_battle_landing"}]},"skill2":{"slots":{"DAMAGEAREA":{"attachment":[{"time":0.9333,"name":"DAMAGEAREA"},{"time":2.5333,"name":null}]},"EF_fire1_1":{"attachment":[{"time":2.5666,"name":"EF/EF_fire/ef_fire_main_00001"},{"time":2.6,"name":"EF/EF_fire/ef_fire_main_00002"},{"time":2.6333,"name":"EF/EF_fire/ef_fire_main_00003"},{"time":2.6666,"name":"EF/EF_fire/ef_fire_main_00004"},{"time":2.7,"name":"EF/EF_fire/ef_fire_main_00005"},{"time":2.7333,"name":"EF/EF_fire/ef_fire_main_00006"},{"time":2.7666,"name":"EF/EF_fire/ef_fire_main_00007"},{"time":2.8,"name":"EF/EF_fire/ef_fire_main_00008"},{"time":2.8333,"name":"EF/EF_fire/ef_fire_main_00009"},{"time":2.8666,"name":"EF/EF_fire/ef_fire_main_00010"},{"time":2.9,"name":"EF/EF_fire/ef_fire_main_00011"},{"time":2.9333,"name":"EF/EF_fire/ef_fire_main_00012"},{"time":2.9666,"name":"EF/EF_fire/ef_fire_main_00013"},{"time":3,"name":"EF/EF_fire/ef_fire_main_00014"},{"time":3.0333,"name":"EF/EF_fire/ef_fire_main_00015"},{"time":3.0666,"name":null}]},"EF_fire1_2":{"attachment":[{"time":2.6333,"name":"EF/EF_fire/ef_fire_main_00001"},{"time":2.6666,"name":"EF/EF_fire/ef_fire_main_00002"},{"time":2.7,"name":"EF/EF_fire/ef_fire_main_00003"},{"time":2.7333,"name":"EF/EF_fire/ef_fire_main_00004"},{"time":2.7666,"name":"EF/EF_fire/ef_fire_main_00005"},{"time":2.8,"name":"EF/EF_fire/ef_fire_main_00006"},{"time":2.8333,"name":"EF/EF_fire/ef_fire_main_00007"},{"time":2.8666,"name":"EF/EF_fire/ef_fire_main_00008"},{"time":2.9,"name":"EF/EF_fire/ef_fire_main_00009"},{"time":2.9333,"name":"EF/EF_fire/ef_fire_main_00010"},{"time":2.9666,"name":"EF/EF_fire/ef_fire_main_00011"},{"time":3,"name":"EF/EF_fire/ef_fire_main_00012"},{"time":3.0333,"name":"EF/EF_fire/ef_fire_main_00013"},{"time":3.0666,"name":"EF/EF_fire/ef_fire_main_00014"},{"time":3.1,"name":"EF/EF_fire/ef_fire_main_00015"},{"time":3.1333,"name":null}]},"EF_smoke1_1":{"attachment":[{"time":2.5666,"name":"EF/ef_smoke_main/ef_smoke_main_00005"},{"time":2.6,"name":"EF/ef_smoke_main/ef_smoke_main_00006"},{"time":2.6666,"name":"EF/ef_smoke_main/ef_smoke_main_00007"},{"time":2.7333,"name":"EF/ef_smoke_main/ef_smoke_main_00008"},{"time":2.8,"name":"EF/ef_smoke_main/ef_smoke_main_00009"},{"time":2.8666,"name":"EF/ef_smoke_main/ef_smoke_main_00010"},{"time":2.9333,"name":"EF/ef_smoke_main/ef_smoke_main_00011"},{"time":3,"name":"EF/ef_smoke_main/ef_smoke_main_00012"},{"time":3.0666,"name":"EF/ef_smoke_main/ef_smoke_main_00013"},{"time":3.1333,"name":"EF/ef_smoke_main/ef_smoke_main_00014"},{"time":3.2,"name":"EF/ef_smoke_main/ef_smoke_main_00015"},{"time":3.2666,"name":"EF/ef_smoke_main/ef_smoke_main_00016"},{"time":3.3333,"name":null}],"color":[{"time":2.5666,"color":"ffffff00"},{"time":2.8333,"color":"ffffffff"},{"time":3.3333,"color":"ffffff00"}]},"EF_smoke1_2":{"attachment":[{"time":2.7,"name":"EF/ef_smoke_main/ef_smoke_main_00008"},{"time":2.7666,"name":"EF/ef_smoke_main/ef_smoke_main_00009"},{"time":2.8333,"name":"EF/ef_smoke_main/ef_smoke_main_00010"},{"time":2.9,"name":"EF/ef_smoke_main/ef_smoke_main_00011"},{"time":2.9666,"name":"EF/ef_smoke_main/ef_smoke_main_00012"},{"time":3.0333,"name":"EF/ef_smoke_main/ef_smoke_main_00013"},{"time":3.1,"name":"EF/ef_smoke_main/ef_smoke_main_00014"},{"time":3.1666,"name":"EF/ef_smoke_main/ef_smoke_main_00015"},{"time":3.2333,"name":"EF/ef_smoke_main/ef_smoke_main_00016"},{"time":3.3,"name":null}],"color":[{"time":2.7,"color":"ffffffff"},{"time":3.3,"color":"ffffff00"}]},"EF_water1_1":{"attachment":[{"time":0.8333,"name":"EF/ef_tuti_main/ef_tuti_main_00001"},{"time":0.8666,"name":"EF/ef_tuti_main/ef_tuti_main_00002"},{"time":0.9,"name":"EF/ef_tuti_main/ef_tuti_main_00003"},{"time":0.9333,"name":"EF/ef_tuti_main/ef_tuti_main_00004"},{"time":0.9666,"name":"EF/ef_tuti_main/ef_tuti_main_00005"},{"time":1,"name":"EF/ef_tuti_main/ef_tuti_main_00006"},{"time":1.0333,"name":"EF/ef_tuti_main/ef_tuti_main_00007"},{"time":1.0666,"name":"EF/ef_tuti_main/ef_tuti_main_00008"},{"time":1.1,"name":"EF/ef_tuti_main/ef_tuti_main_00009"},{"time":1.1333,"name":"EF/ef_tuti_main/ef_tuti_main_00010"},{"time":1.1666,"name":"EF/ef_tuti_main/ef_tuti_main_00011"},{"time":1.2,"name":"EF/ef_tuti_main/ef_tuti_main_00012"},{"time":1.2333,"name":"EF/ef_tuti_main/ef_tuti_main_00013"},{"time":1.2666,"name":"EF/ef_tuti_main/ef_tuti_main_00014"},{"time":1.3,"name":"EF/ef_tuti_main/ef_tuti_main_00015"},{"time":1.3333,"name":"EF/ef_tuti_main/ef_tuti_main_00016"},{"time":1.3666,"name":"EF/ef_tuti_main/ef_tuti_main_00017"},{"time":1.4,"name":null},{"time":1.5,"name":"EF/ef_tuti_main/ef_tuti_main_00001"},{"time":1.5333,"name":"EF/ef_tuti_main/ef_tuti_main_00002"},{"time":1.5666,"name":"EF/ef_tuti_main/ef_tuti_main_00003"},{"time":1.6,"name":"EF/ef_tuti_main/ef_tuti_main_00004"},{"time":1.6333,"name":"EF/ef_tuti_main/ef_tuti_main_00005"},{"time":1.6666,"name":"EF/ef_tuti_main/ef_tuti_main_00006"},{"time":1.7,"name":"EF/ef_tuti_main/ef_tuti_main_00007"},{"time":1.7333,"name":"EF/ef_tuti_main/ef_tuti_main_00008"},{"time":1.7666,"name":"EF/ef_tuti_main/ef_tuti_main_00009"},{"time":1.8,"name":"EF/ef_tuti_main/ef_tuti_main_00010"},{"time":1.8333,"name":"EF/ef_tuti_main/ef_tuti_main_00011"},{"time":1.8666,"name":"EF/ef_tuti_main/ef_tuti_main_00012"},{"time":1.9,"name":"EF/ef_tuti_main/ef_tuti_main_00013"},{"time":1.9333,"name":"EF/ef_tuti_main/ef_tuti_main_00014"},{"time":1.9666,"name":"EF/ef_tuti_main/ef_tuti_main_00015"},{"time":2,"name":"EF/ef_tuti_main/ef_tuti_main_00016"},{"time":2.0333,"name":"EF/ef_tuti_main/ef_tuti_main_00017"},{"time":2.0666,"name":null},{"time":2.1666,"name":"EF/ef_tuti_main/ef_tuti_main_00001"},{"time":2.2,"name":"EF/ef_tuti_main/ef_tuti_main_00002"},{"time":2.2333,"name":"EF/ef_tuti_main/ef_tuti_main_00003"},{"time":2.2666,"name":"EF/ef_tuti_main/ef_tuti_main_00004"},{"time":2.3,"name":"EF/ef_tuti_main/ef_tuti_main_00005"},{"time":2.3333,"name":"EF/ef_tuti_main/ef_tuti_main_00006"},{"time":2.3666,"name":"EF/ef_tuti_main/ef_tuti_main_00007"},{"time":2.4,"name":"EF/ef_tuti_main/ef_tuti_main_00008"},{"time":2.4333,"name":"EF/ef_tuti_main/ef_tuti_main_00009"},{"time":2.4666,"name":"EF/ef_tuti_main/ef_tuti_main_00010"},{"time":2.5,"name":"EF/ef_tuti_main/ef_tuti_main_00011"},{"time":2.5333,"name":"EF/ef_tuti_main/ef_tuti_main_00012"},{"time":2.5666,"name":"EF/ef_tuti_main/ef_tuti_main_00013"},{"time":2.6,"name":"EF/ef_tuti_main/ef_tuti_main_00014"},{"time":2.6333,"name":"EF/ef_tuti_main/ef_tuti_main_00015"},{"time":2.6666,"name":"EF/ef_tuti_main/ef_tuti_main_00016"},{"time":2.7,"name":"EF/ef_tuti_main/ef_tuti_main_00017"},{"time":2.7333,"name":null}]},"EF_water1_2":{"attachment":[{"time":1.1666,"name":"EF/ef_tuti_main/ef_tuti_main_00001"},{"time":1.2,"name":"EF/ef_tuti_main/ef_tuti_main_00002"},{"time":1.2333,"name":"EF/ef_tuti_main/ef_tuti_main_00003"},{"time":1.2666,"name":"EF/ef_tuti_main/ef_tuti_main_00004"},{"time":1.3,"name":"EF/ef_tuti_main/ef_tuti_main_00005"},{"time":1.3333,"name":"EF/ef_tuti_main/ef_tuti_main_00006"},{"time":1.3666,"name":"EF/ef_tuti_main/ef_tuti_main_00007"},{"time":1.4,"name":"EF/ef_tuti_main/ef_tuti_main_00008"},{"time":1.4333,"name":"EF/ef_tuti_main/ef_tuti_main_00009"},{"time":1.4666,"name":"EF/ef_tuti_main/ef_tuti_main_00010"},{"time":1.5,"name":"EF/ef_tuti_main/ef_tuti_main_00011"},{"time":1.5333,"name":"EF/ef_tuti_main/ef_tuti_main_00012"},{"time":1.5666,"name":"EF/ef_tuti_main/ef_tuti_main_00013"},{"time":1.6,"name":"EF/ef_tuti_main/ef_tuti_main_00014"},{"time":1.6333,"name":"EF/ef_tuti_main/ef_tuti_main_00015"},{"time":1.6666,"name":"EF/ef_tuti_main/ef_tuti_main_00016"},{"time":1.7,"name":"EF/ef_tuti_main/ef_tuti_main_00017"},{"time":1.7333,"name":null},{"time":1.8333,"name":"EF/ef_tuti_main/ef_tuti_main_00001"},{"time":1.8666,"name":"EF/ef_tuti_main/ef_tuti_main_00002"},{"time":1.9,"name":"EF/ef_tuti_main/ef_tuti_main_00003"},{"time":1.9333,"name":"EF/ef_tuti_main/ef_tuti_main_00004"},{"time":1.9666,"name":"EF/ef_tuti_main/ef_tuti_main_00005"},{"time":2,"name":"EF/ef_tuti_main/ef_tuti_main_00006"},{"time":2.0333,"name":"EF/ef_tuti_main/ef_tuti_main_00007"},{"time":2.0666,"name":"EF/ef_tuti_main/ef_tuti_main_00008"},{"time":2.1,"name":"EF/ef_tuti_main/ef_tuti_main_00009"},{"time":2.1333,"name":"EF/ef_tuti_main/ef_tuti_main_00010"},{"time":2.1666,"name":"EF/ef_tuti_main/ef_tuti_main_00011"},{"time":2.2,"name":"EF/ef_tuti_main/ef_tuti_main_00012"},{"time":2.2333,"name":"EF/ef_tuti_main/ef_tuti_main_00013"},{"time":2.2666,"name":"EF/ef_tuti_main/ef_tuti_main_00014"},{"time":2.3,"name":"EF/ef_tuti_main/ef_tuti_main_00015"},{"time":2.3333,"name":"EF/ef_tuti_main/ef_tuti_main_00016"},{"time":2.3666,"name":"EF/ef_tuti_main/ef_tuti_main_00017"},{"time":2.4,"name":null}]},"MAIN":{"attachment":[{"time":0,"name":"skill2_00"},{"time":0.1,"name":"skill2_01"},{"time":0.1666,"name":"skill2_02"},{"time":0.2666,"name":"skill2_03"},{"time":0.4,"name":"skill2_04"},{"time":0.4666,"name":"skill2_05"},{"time":0.5666,"name":"skill2_06"},{"time":0.7,"name":"skill2_07"},{"time":0.8333,"name":"skill2_07"},{"time":0.8666,"name":"skill2_08"},{"time":0.9333,"name":"skill2_09"},{"time":0.9666,"name":"skill2_08"},{"time":1,"name":"skill2_09"},{"time":1.0333,"name":"skill2_08"},{"time":1.0666,"name":"skill2_09"},{"time":1.1,"name":"skill2_08"},{"time":1.1333,"name":"skill2_09"},{"time":1.1666,"name":"skill2_08"},{"time":1.2,"name":"skill2_09"},{"time":1.2333,"name":"skill2_08"},{"time":1.2666,"name":"skill2_09"},{"time":1.3,"name":"skill2_08"},{"time":1.3333,"name":"skill2_09"},{"time":1.3666,"name":"skill2_08"},{"time":1.4,"name":"skill2_09"},{"time":1.4333,"name":"skill2_08"},{"time":1.4666,"name":"skill2_09"},{"time":1.5,"name":"skill2_08"},{"time":1.5333,"name":"skill2_09"},{"time":1.5666,"name":"skill2_08"},{"time":1.6,"name":"skill2_09"},{"time":1.6333,"name":"skill2_08"},{"time":1.6666,"name":"skill2_09"},{"time":1.7,"name":"skill2_08"},{"time":1.7333,"name":"skill2_09"},{"time":1.7666,"name":"skill2_08"},{"time":1.8,"name":"skill2_09"},{"time":1.8333,"name":"skill2_08"},{"time":1.9,"name":"skill2_09"},{"time":1.9666,"name":"skill2_08"},{"time":2.0333,"name":"skill2_09"},{"time":2.1,"name":"skill2_08"},{"time":2.1666,"name":"skill2_09"},{"time":2.2333,"name":"skill2_08"},{"time":2.3,"name":"skill2_09"},{"time":2.3666,"name":"skill2_08"},{"time":2.4333,"name":"skill2_09"},{"time":2.5666,"name":"skill2_10"},{"time":2.8333,"name":"skill2_11"},{"time":3,"name":"in_01"},{"time":3.1,"name":"skill2_01"},{"time":3.2,"name":"attack1_13"},{"time":3.3333,"name":"idle_00"}]},"eye":{"attachment":[{"time":0.1,"name":"EF/eye_EF/eye_skill2_01"},{"time":0.1666,"name":"EF/eye_EF/eye_skill2_02"},{"time":0.2666,"name":"EF/eye_EF/eye_skill2_03"},{"time":0.3,"name":"EF/eye_EF/eye_skill2_03_2"},{"time":0.3666,"name":"EF/eye_EF/eye_skill2_03_3"},{"time":0.4,"name":"EF/eye_EF/eye_skill2_04"},{"time":0.4666,"name":"EF/eye_EF/eye_skill2_05"},{"time":0.5666,"name":"EF/eye_EF/eye_skill2_06"},{"time":0.7,"name":"EF/eye_EF/eye_skill2_07"},{"time":0.8666,"name":"EF/eye_EF/eye_skill2_08"},{"time":0.9333,"name":"EF/eye_EF/eye_skill2_09"},{"time":0.9666,"name":"EF/eye_EF/eye_skill2_08"},{"time":1,"name":"EF/eye_EF/eye_skill2_09"},{"time":1.0333,"name":"EF/eye_EF/eye_skill2_08"},{"time":1.0666,"name":"EF/eye_EF/eye_skill2_09"},{"time":1.1,"name":"EF/eye_EF/eye_skill2_08"},{"time":1.1333,"name":"EF/eye_EF/eye_skill2_09"},{"time":1.1666,"name":"EF/eye_EF/eye_skill2_08"},{"time":1.2,"name":"EF/eye_EF/eye_skill2_09"},{"time":1.2333,"name":"EF/eye_EF/eye_skill2_08"},{"time":1.2666,"name":"EF/eye_EF/eye_skill2_09"},{"time":1.3,"name":"EF/eye_EF/eye_skill2_08"},{"time":1.3333,"name":"EF/eye_EF/eye_skill2_09"},{"time":1.3666,"name":"EF/eye_EF/eye_skill2_08"},{"time":1.4,"name":"EF/eye_EF/eye_skill2_09"},{"time":1.4333,"name":"EF/eye_EF/eye_skill2_08"},{"time":1.4666,"name":"EF/eye_EF/eye_skill2_09"},{"time":1.5,"name":"EF/eye_EF/eye_skill2_08"},{"time":1.5333,"name":"EF/eye_EF/eye_skill2_09"},{"time":1.5666,"name":"EF/eye_EF/eye_skill2_08"},{"time":1.6,"name":"EF/eye_EF/eye_skill2_09"},{"time":1.6333,"name":"EF/eye_EF/eye_skill2_08"},{"time":1.6666,"name":"EF/eye_EF/eye_skill2_09"},{"time":1.7,"name":"EF/eye_EF/eye_skill2_08"},{"time":1.7333,"name":"EF/eye_EF/eye_skill2_09"},{"time":1.7666,"name":"EF/eye_EF/eye_skill2_08"},{"time":1.8,"name":"EF/eye_EF/eye_skill2_09"},{"time":1.8333,"name":"EF/eye_EF/eye_skill2_08"},{"time":1.9,"name":"EF/eye_EF/eye_skill2_09"},{"time":1.9666,"name":"EF/eye_EF/eye_skill2_08"},{"time":2.0333,"name":"EF/eye_EF/eye_skill2_09"},{"time":2.1,"name":"EF/eye_EF/eye_skill2_08"},{"time":2.1666,"name":"EF/eye_EF/eye_skill2_09"},{"time":2.2333,"name":"EF/eye_EF/eye_skill2_08"},{"time":2.3,"name":"EF/eye_EF/eye_skill2_09"},{"time":2.3666,"name":"EF/eye_EF/eye_skill2_08"},{"time":2.4333,"name":"EF/eye_EF/eye_skill2_09"},{"time":2.5666,"name":"EF/eye_EF/eye_skill2_10"},{"time":2.8333,"name":"EF/eye_EF/eye_skill2_01"},{"time":3.3333,"name":null}],"color":[{"time":3.1,"color":"ffffffff"},{"time":3.3333,"color":"ffffff00"}]}},"bones":{"MAIN":{"translate":[{"time":0.5666,"x":12.71,"y":0,"curve":"stepped"},{"time":0.7,"x":26.76,"y":0,"curve":"stepped"},{"time":0.8333,"x":26.76,"y":0,"curve":"stepped"},{"time":3,"x":8.79,"y":0,"curve":"stepped"},{"time":3.1,"x":-1.44,"y":0,"curve":"stepped"},{"time":3.2,"x":0,"y":0,"curve":"stepped"},{"time":3.3333,"x":0,"y":0}]},"eye":{"translate":[{"time":2.8333,"x":-4.08,"y":-15.33,"curve":"stepped"},{"time":3,"x":-13.42,"y":-22.25,"curve":"stepped"},{"time":3.1,"x":1.44,"y":2.66}]},"EF_fire1_1":{"rotate":[{"time":2.5666,"angle":-8.97}],"translate":[{"time":2.5666,"x":-192.58,"y":-28.15}],"scale":[{"time":2.5666,"x":1,"y":1}]},"EF_fire1_2":{"rotate":[{"time":2.6333,"angle":8.83}],"translate":[{"time":2.6333,"x":-177.38,"y":-7.42}],"scale":[{"time":2.6333,"x":1,"y":1}]},"EF_smoke1_1":{"rotate":[{"time":2.5666,"angle":-47.73}],"translate":[{"time":2.5666,"x":-284.53,"y":-13.03}],"scale":[{"time":2.5666,"x":1,"y":1},{"time":3.3,"x":1.235,"y":1.235}]},"EF_smoke1_2":{"rotate":[{"time":2.7,"angle":-15.1}],"translate":[{"time":2.7,"x":-248.05,"y":16.96}],"scale":[{"time":2.7,"x":1.356,"y":1.356}]},"EF_water1_1":{"translate":[{"time":0.8333,"x":-218.96,"y":0}],"scale":[{"time":0.8333,"x":2.5,"y":2.5}]},"EF_water1_2":{"translate":[{"time":1.1666,"x":-218.96,"y":0}],"scale":[{"time":1.1666,"x":2.5,"y":2.5}]},"DAMAGEAREA":{"translate":[{"time":0.9333,"x":-609.87,"y":99.53}],"scale":[{"time":0.9333,"x":18.476,"y":4.518}]}},"events":[{"time":0,"name":"Event","string":"setHitEffect(hit08b, 0)"},{"time":0,"name":"Sound3","string":"setHitSound(se_battle_007_attack_hit_01)"},{"time":0,"name":"Voice","string":"cri_718_voice_fullarts_now"},{"time":0.7,"name":"Sound1","string":"cri_se_battle_skill_reaper"},{"time":0.9333,"name":"Event","float":0.18,"string":"kHitStopType_normal"},{"time":0.9333,"name":"Event2","float":1.5,"string":"shakeGround"},{"time":0.9666,"name":"Event","float":1.7,"string":"shakeGround_Loop"},{"time":1,"name":"Event","float":0.06,"string":"kHitStopType_enemyonly"},{"time":1,"name":"Hit","string":"resetHitList"},{"time":1.0333,"name":"Voice","string":"cri_718_voice_fullarts_rank5_a"},{"time":1.0666,"name":"Hit","string":"resetHitList"},{"time":1.1333,"name":"Hit","string":"resetHitList"},{"time":1.2,"name":"Hit","string":"resetHitList"},{"time":1.2666,"name":"Hit","string":"resetHitList"},{"time":1.3333,"name":"Hit","string":"resetHitList"},{"time":1.4,"name":"Hit","string":"resetHitList"},{"time":1.4666,"name":"Hit","string":"resetHitList"},{"time":1.4666,"name":"Sound1","string":"cri_se_battle_darkness_explosion"},{"time":1.5333,"name":"Hit","string":"resetHitList"},{"time":1.6,"name":"Hit","string":"resetHitList"},{"time":1.6666,"name":"Hit","string":"resetHitList"},{"time":1.7333,"name":"Hit","string":"resetHitList"},{"time":1.8,"name":"Hit","string":"resetHitList"},{"time":1.8666,"name":"Hit","string":"resetHitList"},{"time":1.9333,"name":"Hit","string":"resetHitList"},{"time":2,"name":"Hit","string":"resetHitList"},{"time":2.0666,"name":"Hit","string":"resetHitList"},{"time":2.1333,"name":"Hit","string":"resetHitList"},{"time":2.2,"name":"Hit","string":"resetHitList"},{"time":2.2666,"name":"Hit","string":"resetHitList"},{"time":2.3333,"name":"Hit","string":"resetHitList"},{"time":2.4,"name":"Hit","string":"resetHitList"},{"time":2.4666,"name":"Event","float":0.15,"string":"kHitStopType_normal"},{"time":2.4666,"name":"Event2","float":1.7,"string":"shakeGround"},{"time":2.4666,"name":"Hit","string":"resetHitList"}]},"skill3":{"slots":{"DAMAGEAREA":{"attachment":[{"time":0.7333,"name":"DAMAGEAREA"},{"time":0.8,"name":null},{"time":1.5,"name":"DAMAGEAREA"},{"time":1.5666,"name":null},{"time":1.8666,"name":"DAMAGEAREA"},{"time":1.9333,"name":null},{"time":2.2333,"name":"DAMAGEAREA"},{"time":2.3,"name":null},{"time":2.5666,"name":"DAMAGEAREA"},{"time":2.6333,"name":null},{"time":3,"name":"DAMAGEAREA"},{"time":3.0666,"name":null},{"time":3.3666,"name":"DAMAGEAREA"},{"time":3.4333,"name":null},{"time":4.2333,"name":"DAMAGEAREA"},{"time":4.3,"name":null}]},"EF_dash1_1":{"attachment":[{"time":0.3333,"name":"EF/ef_dash_main/ef_dash_main_00001"},{"time":0.3666,"name":"EF/ef_dash_main/ef_dash_main_00003"},{"time":0.4,"name":"EF/ef_dash_main/ef_dash_main_00005"},{"time":0.4333,"name":"EF/ef_dash_main/ef_dash_main_00007"},{"time":0.4666,"name":"EF/ef_dash_main/ef_dash_main_00009"},{"time":0.5,"name":"EF/ef_dash_main/ef_dash_main_00010"},{"time":0.5333,"name":"EF/ef_dash_main/ef_dash_main_00011"},{"time":0.5666,"name":"EF/ef_dash_main/ef_dash_main_00012"},{"time":0.6,"name":"EF/ef_dash_main/ef_dash_main_00013"},{"time":0.6333,"name":null},{"time":0.7333,"name":"EF/ef_dash_main/ef_dash_main_00001"},{"time":0.7666,"name":"EF/ef_dash_main/ef_dash_main_00003"},{"time":0.8,"name":"EF/ef_dash_main/ef_dash_main_00005"},{"time":0.8333,"name":"EF/ef_dash_main/ef_dash_main_00007"},{"time":0.8666,"name":"EF/ef_dash_main/ef_dash_main_00009"},{"time":0.9,"name":"EF/ef_dash_main/ef_dash_main_00010"},{"time":0.9333,"name":"EF/ef_dash_main/ef_dash_main_00011"},{"time":0.9666,"name":"EF/ef_dash_main/ef_dash_main_00012"},{"time":1,"name":"EF/ef_dash_main/ef_dash_main_00013"},{"time":1.0333,"name":null},{"time":1.5333,"name":"EF/ef_dash_main/ef_dash_main_00001"},{"time":1.5666,"name":"EF/ef_dash_main/ef_dash_main_00003"},{"time":1.6,"name":"EF/ef_dash_main/ef_dash_main_00005"},{"time":1.6333,"name":"EF/ef_dash_main/ef_dash_main_00007"},{"time":1.6666,"name":"EF/ef_dash_main/ef_dash_main_00009"},{"time":1.7,"name":"EF/ef_dash_main/ef_dash_main_00010"},{"time":1.7333,"name":"EF/ef_dash_main/ef_dash_main_00011"},{"time":1.7666,"name":"EF/ef_dash_main/ef_dash_main_00012"},{"time":1.8,"name":"EF/ef_dash_main/ef_dash_main_00013"},{"time":1.8333,"name":null},{"time":1.8666,"name":"EF/ef_dash_main/ef_dash_main_00001"},{"time":1.9,"name":"EF/ef_dash_main/ef_dash_main_00003"},{"time":1.9333,"name":"EF/ef_dash_main/ef_dash_main_00005"},{"time":1.9666,"name":"EF/ef_dash_main/ef_dash_main_00007"},{"time":2,"name":"EF/ef_dash_main/ef_dash_main_00009"},{"time":2.0333,"name":"EF/ef_dash_main/ef_dash_main_00010"},{"time":2.0666,"name":"EF/ef_dash_main/ef_dash_main_00011"},{"time":2.1,"name":"EF/ef_dash_main/ef_dash_main_00012"},{"time":2.1333,"name":"EF/ef_dash_main/ef_dash_main_00013"},{"time":2.1666,"name":null},{"time":2.2333,"name":"EF/ef_dash_main/ef_dash_main_00001"},{"time":2.2666,"name":"EF/ef_dash_main/ef_dash_main_00003"},{"time":2.3,"name":"EF/ef_dash_main/ef_dash_main_00005"},{"time":2.3333,"name":"EF/ef_dash_main/ef_dash_main_00007"},{"time":2.3666,"name":"EF/ef_dash_main/ef_dash_main_00009"},{"time":2.4,"name":"EF/ef_dash_main/ef_dash_main_00010"},{"time":2.4333,"name":"EF/ef_dash_main/ef_dash_main_00011"},{"time":2.4666,"name":"EF/ef_dash_main/ef_dash_main_00012"},{"time":2.5,"name":"EF/ef_dash_main/ef_dash_main_00013"},{"time":2.5333,"name":null},{"time":2.6,"name":"EF/ef_dash_main/ef_dash_main_00001"},{"time":2.6333,"name":"EF/ef_dash_main/ef_dash_main_00003"},{"time":2.6666,"name":"EF/ef_dash_main/ef_dash_main_00005"},{"time":2.7,"name":"EF/ef_dash_main/ef_dash_main_00007"},{"time":2.7333,"name":"EF/ef_dash_main/ef_dash_main_00009"},{"time":2.7666,"name":"EF/ef_dash_main/ef_dash_main_00010"},{"time":2.8,"name":"EF/ef_dash_main/ef_dash_main_00011"},{"time":2.8333,"name":"EF/ef_dash_main/ef_dash_main_00012"},{"time":2.8666,"name":"EF/ef_dash_main/ef_dash_main_00013"},{"time":2.9,"name":null},{"time":3,"name":"EF/ef_dash_main/ef_dash_main_00001"},{"time":3.0333,"name":"EF/ef_dash_main/ef_dash_main_00003"},{"time":3.0666,"name":"EF/ef_dash_main/ef_dash_main_00005"},{"time":3.1,"name":"EF/ef_dash_main/ef_dash_main_00007"},{"time":3.1333,"name":"EF/ef_dash_main/ef_dash_main_00009"},{"time":3.1666,"name":"EF/ef_dash_main/ef_dash_main_00010"},{"time":3.2,"name":"EF/ef_dash_main/ef_dash_main_00011"},{"time":3.2333,"name":"EF/ef_dash_main/ef_dash_main_00012"},{"time":3.2666,"name":"EF/ef_dash_main/ef_dash_main_00013"},{"time":3.3,"name":null},{"time":3.3666,"name":"EF/ef_dash_main/ef_dash_main_00001"},{"time":3.4,"name":"EF/ef_dash_main/ef_dash_main_00003"},{"time":3.4333,"name":"EF/ef_dash_main/ef_dash_main_00005"},{"time":3.4666,"name":"EF/ef_dash_main/ef_dash_main_00007"},{"time":3.5,"name":"EF/ef_dash_main/ef_dash_main_00009"},{"time":3.5333,"name":"EF/ef_dash_main/ef_dash_main_00010"},{"time":3.5666,"name":"EF/ef_dash_main/ef_dash_main_00011"},{"time":3.6,"name":"EF/ef_dash_main/ef_dash_main_00012"},{"time":3.6333,"name":"EF/ef_dash_main/ef_dash_main_00013"},{"time":3.6666,"name":null}]},"EF_eye":{"attachment":[{"time":4.2,"name":"EF/eye_aura/ef_eye_aura_main_00001"},{"time":4.2333,"name":"EF/eye_aura/ef_eye_aura_main_00002"},{"time":4.2666,"name":"EF/eye_aura/ef_eye_aura_main_00003"},{"time":4.3,"name":"EF/eye_aura/ef_eye_aura_main_00004"},{"time":4.3333,"name":"EF/eye_aura/ef_eye_aura_main_00005"},{"time":4.3666,"name":"EF/eye_aura/ef_eye_aura_main_00006"},{"time":4.4,"name":"EF/eye_aura/ef_eye_aura_main_00007"},{"time":4.4333,"name":"EF/eye_aura/ef_eye_aura_main_00008"},{"time":4.4666,"name":"EF/eye_aura/ef_eye_aura_main_00009"},{"time":4.5,"name":"EF/eye_aura/ef_eye_aura_main_00010"},{"time":4.5333,"name":"EF/eye_aura/ef_eye_aura_main_00011"},{"time":4.5666,"name":"EF/eye_aura/ef_eye_aura_main_00012"},{"time":4.6,"name":"EF/eye_aura/ef_eye_aura_main_00013"},{"time":4.6333,"name":"EF/eye_aura/ef_eye_aura_main_00014"},{"time":4.6666,"name":"EF/eye_aura/ef_eye_aura_main_00015"},{"time":4.7,"name":"EF/eye_aura/ef_eye_aura_main_00016"},{"time":4.7333,"name":"EF/eye_aura/ef_eye_aura_main_00017"},{"time":4.7666,"name":"EF/eye_aura/ef_eye_aura_main_00018"},{"time":4.8,"name":"EF/eye_aura/ef_eye_aura_main_00019"},{"time":4.8333,"name":"EF/eye_aura/ef_eye_aura_main_00020"},{"time":4.8666,"name":"EF/eye_aura/ef_eye_aura_main_00021"},{"time":4.9,"name":"EF/eye_aura/ef_eye_aura_main_00022"},{"time":4.9333,"name":"EF/eye_aura/ef_eye_aura_main_00023"},{"time":4.9666,"name":"EF/eye_aura/ef_eye_aura_main_00024"},{"time":5,"name":null}]},"EF_eye_ray1_1":{"attachment":[{"time":0.1,"name":"EF/ef_stamp_main/ef_stamp_main_00001"},{"time":0.1333,"name":"EF/ef_stamp_main/ef_stamp_main_00002"},{"time":0.1666,"name":"EF/ef_stamp_main/ef_stamp_main_00003"},{"time":0.2,"name":"EF/ef_stamp_main/ef_stamp_main_00004"},{"time":0.3333,"name":null}],"color":[{"time":0.1,"color":"ffffffff","curve":"stepped"},{"time":0.1666,"color":"ffffffff"},{"time":0.3333,"color":"ffffff00"}]},"EF_line1_1":{"attachment":[{"time":4.2,"name":"EF/ef_slash_line_main 2_00004"}],"color":[{"time":4.3666,"color":"ffffffff","curve":[0.25,0,0.811,0.33]},{"time":5.0333,"color":"ffffff00"}]},"EF_slash1_1":{"attachment":[{"time":1.7666,"name":"EF/EF_slash1_1/ef_slash_A_main_00001"},{"time":1.8,"name":"EF/EF_slash1_1/ef_slash_A_main_00002"},{"time":1.8333,"name":"EF/EF_slash1_1/ef_slash_A_main_00003"},{"time":1.8666,"name":"EF/EF_slash1_1/ef_slash_A_main_00004"},{"time":1.9,"name":"EF/EF_slash1_1/ef_slash_A_main_00005"},{"time":1.9333,"name":"EF/EF_slash1_1/ef_slash_A_main_00006"},{"time":1.9666,"name":"EF/EF_slash1_1/ef_slash_A_main_00007"},{"time":2,"name":"EF/EF_slash1_1/ef_slash_A_main_00008"},{"time":2.0333,"name":"EF/EF_slash1_1/ef_slash_A_main_00009"},{"time":2.0666,"name":"EF/EF_slash1_1/ef_slash_A_main_00010"},{"time":2.1,"name":"EF/EF_slash1_1/ef_slash_A_main_00011"},{"time":2.1333,"name":"EF/EF_slash1_1/ef_slash_A_main_00012"},{"time":2.1666,"name":"EF/EF_slash1_1/ef_slash_A_main_00013"},{"time":2.2,"name":null},{"time":3.2666,"name":"EF/EF_slash1_1/ef_slash_A_main_00001"},{"time":3.3,"name":"EF/EF_slash1_1/ef_slash_A_main_00002"},{"time":3.3333,"name":"EF/EF_slash1_1/ef_slash_A_main_00003"},{"time":3.3666,"name":"EF/EF_slash1_1/ef_slash_A_main_00004"},{"time":3.4,"name":"EF/EF_slash1_1/ef_slash_A_main_00005"},{"time":3.4333,"name":"EF/EF_slash1_1/ef_slash_A_main_00006"},{"time":3.4666,"name":"EF/EF_slash1_1/ef_slash_A_main_00007"},{"time":3.5,"name":"EF/EF_slash1_1/ef_slash_A_main_00008"},{"time":3.5333,"name":"EF/EF_slash1_1/ef_slash_A_main_00009"},{"time":3.5666,"name":"EF/EF_slash1_1/ef_slash_A_main_00010"},{"time":3.6,"name":"EF/EF_slash1_1/ef_slash_A_main_00011"},{"time":3.6333,"name":"EF/EF_slash1_1/ef_slash_A_main_00012"},{"time":3.6666,"name":"EF/EF_slash1_1/ef_slash_A_main_00013"},{"time":3.7,"name":null}]},"EF_slash2_1":{"attachment":[{"time":1.4,"name":"EF/EF_slash2_1/ef_slash_B_main_00001"},{"time":1.4333,"name":"EF/EF_slash2_1/ef_slash_B_main_00002"},{"time":1.4666,"name":"EF/EF_slash2_1/ef_slash_B_main_00003"},{"time":1.5,"name":"EF/EF_slash2_1/ef_slash_B_main_00004"},{"time":1.5333,"name":"EF/EF_slash2_1/ef_slash_B_main_00005"},{"time":1.5666,"name":"EF/EF_slash2_1/ef_slash_B_main_00006"},{"time":1.6,"name":"EF/EF_slash2_1/ef_slash_B_main_00007"},{"time":1.6333,"name":"EF/EF_slash2_1/ef_slash_B_main_00008"},{"time":1.6666,"name":"EF/EF_slash2_1/ef_slash_B_main_00009"},{"time":1.7,"name":"EF/EF_slash2_1/ef_slash_B_main_00010"},{"time":1.7333,"name":"EF/EF_slash2_1/ef_slash_B_main_00011"},{"time":1.7666,"name":"EF/EF_slash2_1/ef_slash_B_main_00012"},{"time":1.8,"name":"EF/EF_slash2_1/ef_slash_B_main_00013"},{"time":1.8333,"name":"EF/EF_slash2_1/ef_slash_B_main_00014"},{"time":1.8666,"name":null},{"time":2.4666,"name":"EF/EF_slash2_1/ef_slash_B_main_00001"},{"time":2.5,"name":"EF/EF_slash2_1/ef_slash_B_main_00002"},{"time":2.5333,"name":"EF/EF_slash2_1/ef_slash_B_main_00003"},{"time":2.5666,"name":"EF/EF_slash2_1/ef_slash_B_main_00004"},{"time":2.6,"name":"EF/EF_slash2_1/ef_slash_B_main_00005"},{"time":2.6333,"name":"EF/EF_slash2_1/ef_slash_B_main_00006"},{"time":2.6666,"name":"EF/EF_slash2_1/ef_slash_B_main_00007"},{"time":2.7,"name":"EF/EF_slash2_1/ef_slash_B_main_00008"},{"time":2.7333,"name":"EF/EF_slash2_1/ef_slash_B_main_00009"},{"time":2.7666,"name":"EF/EF_slash2_1/ef_slash_B_main_00010"},{"time":2.8,"name":"EF/EF_slash2_1/ef_slash_B_main_00011"},{"time":2.8333,"name":"EF/EF_slash2_1/ef_slash_B_main_00012"},{"time":2.8666,"name":"EF/EF_slash2_1/ef_slash_B_main_00013"},{"time":2.9,"name":"EF/EF_slash2_1/ef_slash_B_main_00014"},{"time":2.9333,"name":null}]},"EF_slash3_1":{"attachment":[{"time":2.2,"name":"EF/ef_slash_C_main/ef_slash_C_main_00001"},{"time":2.2333,"name":"EF/ef_slash_C_main/ef_slash_C_main_00002"},{"time":2.2666,"name":"EF/ef_slash_C_main/ef_slash_C_main_00003"},{"time":2.3,"name":"EF/ef_slash_C_main/ef_slash_C_main_00004"},{"time":2.3333,"name":"EF/ef_slash_C_main/ef_slash_C_main_00005"},{"time":2.3666,"name":"EF/ef_slash_C_main/ef_slash_C_main_00006"},{"time":2.4,"name":"EF/ef_slash_C_main/ef_slash_C_main_00007"},{"time":2.4333,"name":"EF/ef_slash_C_main/ef_slash_C_main_00008"},{"time":2.4666,"name":"EF/ef_slash_C_main/ef_slash_C_main_00009"},{"time":2.5,"name":"EF/ef_slash_C_main/ef_slash_C_main_00010"},{"time":2.5333,"name":"EF/ef_slash_C_main/ef_slash_C_main_00011"},{"time":2.5666,"name":"EF/ef_slash_C_main/ef_slash_C_main_00012"},{"time":2.6,"name":null},{"time":2.9666,"name":"EF/ef_slash_C_main/ef_slash_C_main_00001"},{"time":3,"name":"EF/ef_slash_C_main/ef_slash_C_main_00002"},{"time":3.0333,"name":"EF/ef_slash_C_main/ef_slash_C_main_00003"},{"time":3.0666,"name":"EF/ef_slash_C_main/ef_slash_C_main_00004"},{"time":3.1,"name":"EF/ef_slash_C_main/ef_slash_C_main_00005"},{"time":3.1333,"name":"EF/ef_slash_C_main/ef_slash_C_main_00006"},{"time":3.1666,"name":"EF/ef_slash_C_main/ef_slash_C_main_00007"},{"time":3.2,"name":"EF/ef_slash_C_main/ef_slash_C_main_00008"},{"time":3.2333,"name":"EF/ef_slash_C_main/ef_slash_C_main_00009"},{"time":3.2666,"name":"EF/ef_slash_C_main/ef_slash_C_main_00010"},{"time":3.3,"name":"EF/ef_slash_C_main/ef_slash_C_main_00011"},{"time":3.3333,"name":"EF/ef_slash_C_main/ef_slash_C_main_00012"},{"time":3.3666,"name":null}]},"EF_wave1_1":{"attachment":[{"time":0.3333,"name":"EF/ef_graund_wave_main/ef_graund_wave_main_00001"},{"time":0.3666,"name":"EF/ef_graund_wave_main/ef_graund_wave_main_00006"},{"time":0.4,"name":"EF/ef_graund_wave_main/ef_graund_wave_main_00007"},{"time":0.4333,"name":"EF/ef_graund_wave_main/ef_graund_wave_main_00008"},{"time":0.4666,"name":"EF/ef_graund_wave_main/ef_graund_wave_main_00009"},{"time":0.5,"name":"EF/ef_graund_wave_main/ef_graund_wave_main_00010"},{"time":0.5333,"name":"EF/ef_graund_wave_main/ef_graund_wave_main_00011"},{"time":0.5666,"name":"EF/ef_graund_wave_main/ef_graund_wave_main_00012"},{"time":0.6,"name":"EF/ef_graund_wave_main/ef_graund_wave_main_00013"},{"time":0.6333,"name":"EF/ef_graund_wave_main/ef_graund_wave_main_00014"},{"time":0.6666,"name":null},{"time":0.7333,"name":"EF/ef_graund_wave_main/ef_graund_wave_main_00001"},{"time":0.7666,"name":"EF/ef_graund_wave_main/ef_graund_wave_main_00003"},{"time":0.8,"name":"EF/ef_graund_wave_main/ef_graund_wave_main_00005"},{"time":0.8333,"name":"EF/ef_graund_wave_main/ef_graund_wave_main_00007"},{"time":0.8666,"name":"EF/ef_graund_wave_main/ef_graund_wave_main_00009"},{"time":0.9,"name":"EF/ef_graund_wave_main/ef_graund_wave_main_00011"},{"time":0.9333,"name":"EF/ef_graund_wave_main/ef_graund_wave_main_00012"},{"time":0.9666,"name":"EF/ef_graund_wave_main/ef_graund_wave_main_00013"},{"time":1,"name":"EF/ef_graund_wave_main/ef_graund_wave_main_00014"},{"time":1.0333,"name":null},{"time":1.5333,"name":"EF/ef_graund_wave_main/ef_graund_wave_main_00001"},{"time":1.5666,"name":"EF/ef_graund_wave_main/ef_graund_wave_main_00003"},{"time":1.6,"name":"EF/ef_graund_wave_main/ef_graund_wave_main_00005"},{"time":1.6333,"name":"EF/ef_graund_wave_main/ef_graund_wave_main_00007"},{"time":1.6666,"name":"EF/ef_graund_wave_main/ef_graund_wave_main_00009"},{"time":1.7,"name":"EF/ef_graund_wave_main/ef_graund_wave_main_00011"},{"time":1.7333,"name":"EF/ef_graund_wave_main/ef_graund_wave_main_00012"},{"time":1.7666,"name":"EF/ef_graund_wave_main/ef_graund_wave_main_00013"},{"time":1.8,"name":"EF/ef_graund_wave_main/ef_graund_wave_main_00014"},{"time":1.8333,"name":null},{"time":1.8666,"name":"EF/ef_graund_wave_main/ef_graund_wave_main_00001"},{"time":1.9,"name":"EF/ef_graund_wave_main/ef_graund_wave_main_00003"},{"time":1.9333,"name":"EF/ef_graund_wave_main/ef_graund_wave_main_00005"},{"time":1.9666,"name":"EF/ef_graund_wave_main/ef_graund_wave_main_00007"},{"time":2,"name":"EF/ef_graund_wave_main/ef_graund_wave_main_00009"},{"time":2.0333,"name":"EF/ef_graund_wave_main/ef_graund_wave_main_00011"},{"time":2.0666,"name":"EF/ef_graund_wave_main/ef_graund_wave_main_00012"},{"time":2.1,"name":"EF/ef_graund_wave_main/ef_graund_wave_main_00013"},{"time":2.1333,"name":"EF/ef_graund_wave_main/ef_graund_wave_main_00014"},{"time":2.1666,"name":null},{"time":2.2333,"name":"EF/ef_graund_wave_main/ef_graund_wave_main_00001"},{"time":2.2666,"name":"EF/ef_graund_wave_main/ef_graund_wave_main_00003"},{"time":2.3,"name":"EF/ef_graund_wave_main/ef_graund_wave_main_00005"},{"time":2.3333,"name":"EF/ef_graund_wave_main/ef_graund_wave_main_00007"},{"time":2.3666,"name":"EF/ef_graund_wave_main/ef_graund_wave_main_00009"},{"time":2.4,"name":"EF/ef_graund_wave_main/ef_graund_wave_main_00011"},{"time":2.4333,"name":"EF/ef_graund_wave_main/ef_graund_wave_main_00012"},{"time":2.4666,"name":"EF/ef_graund_wave_main/ef_graund_wave_main_00013"},{"time":2.5,"name":"EF/ef_graund_wave_main/ef_graund_wave_main_00014"},{"time":2.5333,"name":null},{"time":2.6,"name":"EF/ef_graund_wave_main/ef_graund_wave_main_00001"},{"time":2.6333,"name":"EF/ef_graund_wave_main/ef_graund_wave_main_00003"},{"time":2.6666,"name":"EF/ef_graund_wave_main/ef_graund_wave_main_00005"},{"time":2.7,"name":"EF/ef_graund_wave_main/ef_graund_wave_main_00007"},{"time":2.7333,"name":"EF/ef_graund_wave_main/ef_graund_wave_main_00009"},{"time":2.7666,"name":"EF/ef_graund_wave_main/ef_graund_wave_main_00011"},{"time":2.8,"name":"EF/ef_graund_wave_main/ef_graund_wave_main_00012"},{"time":2.8333,"name":"EF/ef_graund_wave_main/ef_graund_wave_main_00013"},{"time":2.8666,"name":"EF/ef_graund_wave_main/ef_graund_wave_main_00014"},{"time":2.9,"name":null},{"time":3,"name":"EF/ef_graund_wave_main/ef_graund_wave_main_00001"},{"time":3.0333,"name":"EF/ef_graund_wave_main/ef_graund_wave_main_00003"},{"time":3.0666,"name":"EF/ef_graund_wave_main/ef_graund_wave_main_00005"},{"time":3.1,"name":"EF/ef_graund_wave_main/ef_graund_wave_main_00007"},{"time":3.1333,"name":"EF/ef_graund_wave_main/ef_graund_wave_main_00009"},{"time":3.1666,"name":"EF/ef_graund_wave_main/ef_graund_wave_main_00011"},{"time":3.2,"name":"EF/ef_graund_wave_main/ef_graund_wave_main_00012"},{"time":3.2333,"name":"EF/ef_graund_wave_main/ef_graund_wave_main_00013"},{"time":3.2666,"name":"EF/ef_graund_wave_main/ef_graund_wave_main_00014"},{"time":3.3,"name":null},{"time":3.3666,"name":"EF/ef_graund_wave_main/ef_graund_wave_main_00001"},{"time":3.4,"name":"EF/ef_graund_wave_main/ef_graund_wave_main_00003"},{"time":3.4333,"name":"EF/ef_graund_wave_main/ef_graund_wave_main_00005"},{"time":3.4666,"name":"EF/ef_graund_wave_main/ef_graund_wave_main_00007"},{"time":3.5,"name":"EF/ef_graund_wave_main/ef_graund_wave_main_00009"},{"time":3.5333,"name":"EF/ef_graund_wave_main/ef_graund_wave_main_00011"},{"time":3.5666,"name":"EF/ef_graund_wave_main/ef_graund_wave_main_00012"},{"time":3.6,"name":"EF/ef_graund_wave_main/ef_graund_wave_main_00013"},{"time":3.6333,"name":"EF/ef_graund_wave_main/ef_graund_wave_main_00014"},{"time":3.6666,"name":null}]},"MAIN":{"attachment":[{"time":0,"name":"attack1_00"},{"time":0.1,"name":"attack1_01"},{"time":0.3333,"name":"front_00"},{"time":0.7333,"name":"skill1_03"},{"time":0.8,"name":"skill1_04"},{"time":0.9333,"name":"skill1_06"},{"time":1.2,"name":"attack1_05"},{"time":1.2666,"name":"attack1_06"},{"time":1.4,"name":"attack1_07"},{"time":1.4666,"name":"attack1_08"},{"time":1.5333,"name":"skill1_12"},{"time":1.6333,"name":"attack1_00"},{"time":1.7,"name":"attack1_01"},{"time":1.8666,"name":"attack1_03"},{"time":1.9,"name":"attack1_04"},{"time":2.0333,"name":"attack1_05"},{"time":2.0666,"name":"attack1_06"},{"time":2.2,"name":"attack1_07"},{"time":2.2333,"name":"attack1_09"},{"time":2.3666,"name":"attack1_10"},{"time":2.4,"name":"skill1_12"},{"time":2.4333,"name":"attack1_00"},{"time":2.5,"name":"attack1_01"},{"time":2.5333,"name":"attack1_02"},{"time":2.5666,"name":"skill3_00"},{"time":2.6333,"name":"skill1_09"},{"time":2.8333,"name":"skill1_10"},{"time":2.9666,"name":"skill1_11"},{"time":3,"name":"attack1_09"},{"time":3.1,"name":"attack1_10"},{"time":3.1666,"name":"skill1_12"},{"time":3.2,"name":"attack1_00"},{"time":3.2333,"name":"attack1_01"},{"time":3.3333,"name":"attack1_02"},{"time":3.3666,"name":"attack1_03"},{"time":3.4,"name":"attack1_04"},{"time":3.6333,"name":"skill1_06"},{"time":3.7666,"name":"skill1_07"},{"time":3.8666,"name":"skill3_03"},{"time":3.9333,"name":"skill3_04"},{"time":4.2,"name":"skill3_05"},{"time":4.2333,"name":"skill3_06"},{"time":4.2666,"name":"skill3_05"},{"time":4.3,"name":"skill3_06"},{"time":4.3333,"name":"skill3_05"},{"time":4.3666,"name":"skill3_06"},{"time":4.4,"name":"skill3_05"},{"time":4.4333,"name":"skill3_06"},{"time":4.4666,"name":"skill3_05"},{"time":4.5,"name":"skill3_06"},{"time":4.5333,"name":"skill3_05"},{"time":4.5666,"name":"skill3_06"},{"time":4.6,"name":"skill3_05"},{"time":4.6666,"name":"skill3_06"},{"time":4.7333,"name":"skill3_05"},{"time":4.8,"name":"skill3_06"},{"time":4.8666,"name":"skill3_05"},{"time":4.9333,"name":"skill3_06"},{"time":5,"name":"skill3_05"},{"time":5.0666,"name":"skill3_06"},{"time":5.1333,"name":"skill3_05"},{"time":5.2,"name":"skill3_06"},{"time":5.3,"name":"skill1_06"},{"time":5.5333,"name":"attack1_12"},{"time":5.7333,"name":"attack1_14"},{"time":5.8333,"name":"idle_00"}],"color":[{"time":0,"color":"ffffffff"},{"time":0.1,"color":"000000ff","curve":"stepped"},{"time":0.3333,"color":"000000ff"},{"time":0.4333,"color":"00000000","curve":"stepped"},{"time":0.6666,"color":"00000000"},{"time":0.7333,"color":"000000ff"},{"time":0.9333,"color":"ffffffff","curve":"stepped"},{"time":1.4666,"color":"ffffffff"},{"time":1.5333,"color":"000000ff"},{"time":1.6333,"color":"ffffffff","curve":"stepped"},{"time":1.8,"color":"ffffffff"},{"time":1.8666,"color":"000000ff"},{"time":1.9666,"color":"ffffffff","curve":"stepped"},{"time":2.1666,"color":"ffffffff"},{"time":2.2333,"color":"000000ff"},{"time":2.3333,"color":"ffffffff","curve":"stepped"},{"time":2.5333,"color":"ffffffff"},{"time":2.6,"color":"000000ff"},{"time":2.7,"color":"ffffffff","curve":"stepped"},{"time":2.9333,"color":"ffffffff"},{"time":3,"color":"000000ff"},{"time":3.1,"color":"ffffffff","curve":"stepped"},{"time":3.3,"color":"ffffffff"},{"time":3.3666,"color":"000000ff"},{"time":3.4666,"color":"ffffffff","curve":"stepped"},{"time":3.7666,"color":"ffffffff"},{"time":3.8333,"color":"555555ff","curve":"stepped"},{"time":4.1,"color":"555555ff"},{"time":4.1666,"color":"000000ff","curve":"stepped"},{"time":4.6,"color":"000000ff"},{"time":5.2,"color":"ffffffff"}]},"eye":{"attachment":[{"time":0.0666,"name":"EF/eye_EF/eye_attack1_00"},{"time":0.1,"name":"EF/eye_EF/eye_attack1_01"},{"time":0.1666,"name":"EF/eye_EF/eye_skill2_01"},{"time":0.3,"name":"EF/eye_EF/eye_attack1_02"},{"time":0.4333,"name":null},{"time":0.7,"name":"EF/eye_EF/eye_attack1_02"},{"time":0.7333,"name":"EF/eye_EF/eye_attack1_03"},{"time":0.8,"name":"EF/eye_EF/eye_attack1_04"},{"time":0.9333,"name":"EF/eye_EF/eye_skill1_06"},{"time":1.0333,"name":"EF/eye_EF/eye_skill1_07"},{"time":1.2,"name":"EF/eye_EF/eye_attack1_05"},{"time":1.2666,"name":"EF/eye_EF/eye_attack1_06"},{"time":1.4,"name":"EF/eye_EF/eye_attack1_07"},{"time":1.4666,"name":"EF/eye_EF/eye_attack1_08"},{"time":1.5333,"name":"EF/eye_EF/eye_skill1_12"},{"time":1.6333,"name":"EF/eye_EF/eye_attack1_03"},{"time":1.7,"name":"EF/eye_EF/eye_attack1_04"},{"time":1.7666,"name":"EF/eye_EF/eye_attack1_05"},{"time":1.8333,"name":"EF/eye_EF/eye_attack1_15"},{"time":1.8666,"name":"EF/eye_EF/eye_attack1_03"},{"time":1.9,"name":"EF/eye_EF/eye_attack1_04"},{"time":2.0333,"name":"EF/eye_EF/eye_attack1_05"},{"time":2.0666,"name":"EF/eye_EF/eye_attack1_06"},{"time":2.2,"name":"EF/eye_EF/eye_attack1_07"},{"time":2.2333,"name":"EF/eye_EF/eye_skill1_12"},{"time":2.3333,"name":"EF/eye_EF/eye_skill2_04"},{"time":2.3666,"name":"EF/eye_EF/eye_skill2_05"},{"time":2.4,"name":"EF/eye_EF/eye_skill1_12"},{"time":2.4333,"name":"EF/eye_EF/eye_attack1_08"},{"time":2.4666,"name":"EF/eye_EF/eye_attack1_16"},{"time":2.5,"name":"EF/eye_EF/eye_attack1_03"},{"time":2.5333,"name":"EF/eye_EF/eye_attack1_04"},{"time":2.5666,"name":"EF/eye_EF/eye_skill3_00"},{"time":2.6333,"name":"EF/eye_EF/eye_attack1_06"},{"time":2.8333,"name":"EF/eye_EF/eye_skill2_03"},{"time":2.9666,"name":"EF/eye_EF/eye_skill2_04"},{"time":3,"name":"EF/eye_EF/eye_attack1_15"},{"time":3.0666,"name":"EF/eye_EF/eye_attack1_16"},{"time":3.1,"name":"EF/eye_EF/eye_skill2_05"},{"time":3.1666,"name":"EF/eye_EF/eye_skill1_12"},{"time":3.2,"name":"EF/eye_EF/eye_attack1_08"},{"time":3.2333,"name":"EF/eye_EF/eye_attack1_04"},{"time":3.3,"name":"EF/eye_EF/eye_attack1_05"},{"time":3.3333,"name":"EF/eye_EF/eye_attack1_03"},{"time":3.3666,"name":"EF/eye_EF/eye_attack1_03"},{"time":3.4,"name":"EF/eye_EF/eye_attack1_04"},{"time":3.5,"name":"EF/eye_EF/eye_attack1_05"},{"time":3.5666,"name":"EF/eye_EF/eye_skill2_03"},{"time":3.6333,"name":"EF/eye_EF/eye_skill1_06"},{"time":3.7,"name":"EF/eye_EF/eye_skill1_07"},{"time":3.8,"name":"EF/eye_EF/eye_skill1_07"},{"time":3.8666,"name":"EF/eye_EF/eye_skill3_03"},{"time":3.9333,"name":"EF/eye_EF/eye_skill3_04"},{"time":4,"name":null},{"time":4.2,"name":"EF/eye_EF/eye_attack1_00"},{"time":4.2333,"name":"EF/eye_EF/eye_attack1_01"},{"time":4.2666,"name":"EF/eye_EF/eye_skill3_05"},{"time":4.3,"name":"EF/eye_EF/eye_skill3_05_2"},{"time":4.3666,"name":"EF/eye_EF/eye_skill3_06"},{"time":4.4333,"name":"EF/eye_EF/eye_skill3_05"},{"time":4.5,"name":"EF/eye_EF/eye_skill3_06"},{"time":4.5666,"name":"EF/eye_EF/eye_skill3_05"},{"time":4.6333,"name":"EF/eye_EF/eye_skill3_06"},{"time":4.7,"name":"EF/eye_EF/eye_skill3_05"},{"time":4.7666,"name":"EF/eye_EF/eye_skill3_06"},{"time":4.8333,"name":"EF/eye_EF/eye_skill3_05"},{"time":4.9,"name":"EF/eye_EF/eye_skill3_06"},{"time":4.9666,"name":"EF/eye_EF/eye_skill3_05"},{"time":5.0333,"name":"EF/eye_EF/eye_skill2_01"}],"color":[{"time":5,"color":"ffffffff"},{"time":5.3333,"color":"ffffff00"}]}},"bones":{"MAIN":{"translate":[{"time":0.3333,"x":-33.16,"y":0},{"time":0.4333,"x":-975.5,"y":0,"curve":"stepped"},{"time":0.6666,"x":337.52,"y":0},{"time":0.7333,"x":95.59,"y":0},{"time":0.7666,"x":87.58,"y":0},{"time":0.8,"x":50.17,"y":0,"curve":"stepped"},{"time":0.9333,"x":102.27,"y":9.35},{"time":1.0333,"x":208.5,"y":16.34},{"time":1.2,"x":259.86,"y":0},{"time":1.3666,"x":277.08,"y":0,"curve":[0.053,0.72,0.254,0.95]},{"time":1.5333,"x":175.55,"y":0},{"time":1.6,"x":169.45,"y":0,"curve":"stepped"},{"time":1.6333,"x":177.83,"y":0,"curve":[0.094,0.6,0.75,1]},{"time":1.7666,"x":185.86,"y":0,"curve":"stepped"},{"time":1.8333,"x":185.86,"y":0,"curve":[0.049,0.78,0.247,0.9]},{"time":1.9333,"x":157.04,"y":0},{"time":2,"x":154.61,"y":0,"curve":"stepped"},{"time":2.0333,"x":167.94,"y":0},{"time":2.1333,"x":179.09,"y":0,"curve":"stepped"},{"time":2.2,"x":138.17,"y":0,"curve":"stepped"},{"time":2.2333,"x":139.98,"y":0,"curve":[0.151,0.57,0.75,1]},{"time":2.3333,"x":136.32,"y":0,"curve":"stepped"},{"time":2.3666,"x":142.42,"y":0,"curve":[0.151,0.57,0.75,1]},{"time":2.4666,"x":142.96,"y":0,"curve":"stepped"},{"time":2.5333,"x":111.18,"y":0,"curve":"stepped"},{"time":2.5666,"x":90.46,"y":0,"curve":"stepped"},{"time":2.6333,"x":97.99,"y":94.47,"curve":[0.175,0.84,0.75,1]},{"time":2.9333,"x":106.07,"y":133.41},{"time":2.9666,"x":118.19,"y":1,"curve":"stepped"},{"time":3,"x":106.67,"y":0,"curve":"stepped"},{"time":3.1666,"x":106.67,"y":0},{"time":3.2666,"x":119.4,"y":0,"curve":"stepped"},{"time":3.3333,"x":96.24,"y":0,"curve":"stepped"},{"time":3.3666,"x":114.29,"y":0,"curve":[0.106,0.57,0.75,1]},{"time":3.5333,"x":113.07,"y":0,"curve":"stepped"},{"time":3.6333,"x":165.18,"y":8.53,"curve":[0.099,0.68,0.75,1]},{"time":3.9666,"x":310.32,"y":0},{"time":4.1666,"x":313.98,"y":0},{"time":4.2,"x":209.83,"y":0,"curve":[0.162,0.77,0.75,1]},{"time":5.2,"x":198.86,"y":0,"curve":"stepped"},{"time":5.3,"x":233.51,"y":8.81},{"time":5.4333,"x":305.43,"y":17.63},{"time":5.5333,"x":348.04,"y":0,"curve":[0.07,0.27,0.75,1]},{"time":5.7,"x":359.37,"y":0,"curve":"stepped"},{"time":5.7333,"x":367.8,"y":0},{"time":5.8333,"x":373.03,"y":0}]},"EF_line1_1":{"translate":[{"time":4.2,"x":-198,"y":-75.18}],"scale":[{"time":4.2,"x":10.074,"y":0.621},{"time":4.3666,"x":95.463,"y":14.067,"curve":[0.04,0.13,0.75,1]},{"time":5.0333,"x":95.463,"y":13.46}]},"EF_eye_ray1_1":{"translate":[{"time":0.1,"x":-210.17,"y":-12.2}],"scale":[{"time":0.1,"x":1,"y":1,"curve":[0.094,0.61,0.75,1]},{"time":0.3,"x":1.915,"y":1.915}]},"eye":{"translate":[{"time":0.1,"x":0,"y":0,"curve":"stepped"},{"time":0.1666,"x":-0.54,"y":-20.01,"curve":"stepped"},{"time":0.3,"x":27.89,"y":11.4,"curve":"stepped"},{"time":0.3333,"x":6.55,"y":-4.59,"curve":"stepped"},{"time":0.7333,"x":0.23,"y":-5.22,"curve":"stepped"},{"time":0.8,"x":19.85,"y":9.96,"curve":"stepped"},{"time":0.9333,"x":0,"y":0,"curve":"stepped"},{"time":1.0333,"x":16.45,"y":11.39,"curve":"stepped"},{"time":1.2,"x":0,"y":0,"curve":"stepped"},{"time":1.5333,"x":24,"y":-1.77,"curve":"stepped"},{"time":1.6333,"x":12.44,"y":-9.77,"curve":"stepped"},{"time":1.7,"x":17.04,"y":-6.06,"curve":"stepped"},{"time":1.7666,"x":15.11,"y":-5.8,"curve":"stepped"},{"time":1.8333,"x":0.2,"y":-4.28,"curve":"stepped"},{"time":1.8666,"x":0,"y":0,"curve":"stepped"},{"time":2.2333,"x":8.82,"y":-12.9,"curve":"stepped"},{"time":2.3333,"x":-21.04,"y":-50.24,"curve":"stepped"},{"time":2.3666,"x":-28.51,"y":-38.7,"curve":"stepped"},{"time":2.4,"x":26.03,"y":0.2,"curve":"stepped"},{"time":2.4333,"x":-9.95,"y":-15.4,"curve":"stepped"},{"time":2.4666,"x":7.7,"y":3.6,"curve":"stepped"},{"time":2.5,"x":11.77,"y":-10.65,"curve":"stepped"},{"time":2.5333,"x":-12.66,"y":-13.37,"curve":"stepped"},{"time":2.5666,"x":0.23,"y":-5.22,"curve":"stepped"},{"time":2.6333,"x":0.23,"y":5.13,"curve":"stepped"},{"time":2.8333,"x":15.76,"y":-0.69,"curve":"stepped"},{"time":2.9666,"x":5.41,"y":-0.69,"curve":"stepped"},{"time":3,"x":-12.06,"y":-25.94,"curve":"stepped"},{"time":3.0666,"x":-5.59,"y":-23.99,"curve":"stepped"},{"time":3.1,"x":-28.51,"y":-38.7,"curve":"stepped"},{"time":3.1666,"x":26.03,"y":0.2,"curve":"stepped"},{"time":3.2,"x":-9.95,"y":-15.4,"curve":"stepped"},{"time":3.2333,"x":17.04,"y":-6.06,"curve":"stepped"},{"time":3.3,"x":15.11,"y":-5.8,"curve":"stepped"},{"time":3.3333,"x":-18,"y":-19.72,"curve":"stepped"},{"time":3.3666,"x":0,"y":0,"curve":"stepped"},{"time":3.5,"x":-1.94,"y":0.64,"curve":"stepped"},{"time":3.5666,"x":-24.6,"y":-20.71,"curve":"stepped"},{"time":3.6333,"x":0,"y":0,"curve":"stepped"},{"time":3.7,"x":16.18,"y":11,"curve":"stepped"},{"time":3.8,"x":0,"y":0,"curve":"stepped"},{"time":4.2,"x":-14.24,"y":-7.76,"curve":"stepped"},{"time":4.2333,"x":-12.94,"y":-3.88,"curve":"stepped"},{"time":4.2666,"x":0,"y":0,"curve":"stepped"},{"time":5.0333,"x":-13.25,"y":-23.68}]},"EF_eye":{"translate":[{"time":4.2,"x":-69.4,"y":-14.12}]},"EF_wave1_1":{"translate":[{"time":0.3333,"x":-200,"y":0,"curve":"stepped"},{"time":0.7333,"x":-112.71,"y":0,"curve":"stepped"},{"time":1.5333,"x":-10.93,"y":0,"curve":"stepped"},{"time":1.8666,"x":-46.81,"y":0,"curve":"stepped"},{"time":2.2333,"x":-47.71,"y":0,"curve":"stepped"},{"time":2.6,"x":-104.46,"y":0,"curve":"stepped"},{"time":3,"x":-77.57,"y":0,"curve":"stepped"},{"time":3.3666,"x":-79.36,"y":0}],"scale":[{"time":0.3333,"x":2,"y":2}]},"EF_dash1_1":{"translate":[{"time":0.3333,"x":-85.58,"y":0,"curve":"stepped"},{"time":0.7333,"x":-3.92,"y":0,"curve":"stepped"},{"time":1.5333,"x":101.25,"y":0,"curve":"stepped"},{"time":1.8666,"x":78.66,"y":0,"curve":"stepped"},{"time":2.2333,"x":67.85,"y":0,"curve":"stepped"},{"time":2.6,"x":17.25,"y":0,"curve":"stepped"},{"time":3,"x":52.58,"y":0,"curve":"stepped"},{"time":3.3666,"x":43.82,"y":0}],"scale":[{"time":0.3333,"x":2,"y":2,"curve":"stepped"},{"time":0.7333,"x":2,"y":2,"curve":"stepped"},{"time":1.5333,"x":2,"y":2,"curve":"stepped"},{"time":1.8666,"x":2,"y":2,"curve":"stepped"},{"time":2.2333,"x":2,"y":2,"curve":"stepped"},{"time":2.6,"x":2,"y":2,"curve":"stepped"},{"time":3,"x":2,"y":2,"curve":"stepped"},{"time":3.3666,"x":2,"y":2}]},"EF_slash2_1":{"rotate":[{"time":1.4,"angle":51.79,"curve":"stepped"},{"time":2.4666,"angle":-65.95}],"translate":[{"time":1.4,"x":9.26,"y":-2.92,"curve":"stepped"},{"time":2.4666,"x":-74.36,"y":45.95}],"scale":[{"time":1.4,"x":3.5,"y":3.5,"curve":"stepped"},{"time":2.4666,"x":3.5,"y":-3.5}]},"EF_slash3_1":{"rotate":[{"time":2.2,"angle":-20.05,"curve":"stepped"},{"time":2.9666,"angle":360}],"translate":[{"time":2.2,"x":-71.33,"y":-18.15,"curve":"stepped"},{"time":2.9666,"x":-156.93,"y":9.07}],"scale":[{"time":2.2,"x":3.028,"y":3.028,"curve":"stepped"},{"time":2.9666,"x":3.028,"y":3.028}]},"EF_slash1_1":{"rotate":[{"time":1.7666,"angle":-5.41,"curve":"stepped"},{"time":3.2666,"angle":-5.41}],"translate":[{"time":1.7666,"x":-39.7,"y":40.56,"curve":"stepped"},{"time":3.2666,"x":-146.06,"y":40.56}],"scale":[{"time":1.7666,"x":4,"y":2.5,"curve":"stepped"},{"time":3.2666,"x":4,"y":2.5}]},"DAMAGEAREA":{"translate":[{"time":0.7333,"x":-56.98,"y":65.79,"curve":"stepped"},{"time":1.5,"x":71.25,"y":85.02}],"scale":[{"time":0.7333,"x":9.666,"y":5.295,"curve":"stepped"},{"time":1.5,"x":7.772,"y":8.426,"curve":"stepped"},{"time":4.2333,"x":22.199,"y":6.988}]}},"events":[{"time":0,"name":"Voice","string":"cri_718_voice_fullarts_now_b"},{"time":0.3,"name":"Sound1","string":"cri_se_battle_teleport"},{"time":0.3,"name":"Sound2","string":"cri_se_battle_jump"},{"time":0.3666,"name":"Event","string":"ignoreBorder_true"},{"time":0.6666,"name":"Event","string":"setPosition_Target"},{"time":0.7,"name":"Event","float":1,"string":"kHitStopType_enemyonly"},{"time":0.7,"name":"Sound1","string":"cri_se_battle_sword_srash_02"},{"time":0.7,"name":"Sound3","string":"setHitSound(se_battle_swordslash_heavy)"},{"time":0.7333,"name":"Event","float":1.5,"string":"shakeGround"},{"time":0.9333,"name":"Sound2","string":"cri_se_battle_jump"},{"time":1.2,"name":"Sound2","string":"cri_se_battle_landing"},{"time":1.4333,"name":"Event","string":"kHitStopType_normal"},{"time":1.4333,"name":"Sound1","string":"cri_se_battle_sword_srash_02"},{"time":1.4666,"name":"Event","string":"setHitStopTime(0.14,0.5)"},{"time":1.5,"name":"Event","float":1.5,"string":"shakeGround"},{"time":1.5,"name":"Hit","string":"resetHitList"},{"time":1.8,"name":"Sound1","string":"cri_se_battle_sword_srash_02"},{"time":1.8333,"name":"Event","string":"setHitStopTime(0.08,0.5)"},{"time":1.8666,"name":"Event","float":1.5,"string":"shakeGround"},{"time":1.8666,"name":"Hit","string":"resetHitList"},{"time":2.1666,"name":"Sound1","string":"cri_se_battle_sword_srash_02"},{"time":2.2,"name":"Event","string":"setHitStopTime(0.11,0.5)"},{"time":2.2333,"name":"Event","float":1.5,"string":"shakeGround"},{"time":2.2333,"name":"Hit","string":"resetHitList"},{"time":2.5,"name":"Sound1","string":"cri_se_battle_sword_srash_02"},{"time":2.5666,"name":"Event","float":1.5,"string":"shakeGround"},{"time":2.5666,"name":"Hit","string":"resetHitList"},{"time":2.9333,"name":"Sound1","string":"cri_se_battle_sword_srash_02"},{"time":2.9666,"name":"Event","string":"setHitStopTime(0.18,0.5)"},{"time":3,"name":"Event","float":1.5,"string":"shakeGround"},{"time":3,"name":"Hit","string":"resetHitList"},{"time":3.3,"name":"Sound1","string":"cri_se_battle_sword_srash_02"},{"time":3.3333,"name":"Event","string":"setHitStopTime(0.09,0.5)"},{"time":3.3666,"name":"Event","float":1.5,"string":"shakeGround"},{"time":3.3666,"name":"Hit","string":"resetHitList"},{"time":4,"name":"Voice","string":"cri_718_voice_fullarts_rank6"},{"time":4.1666,"name":"Event","float":0.3,"string":"kHitStopType_normal"},{"time":4.1666,"name":"Sound1","string":"cri_se_battle_sword_srash_02"},{"time":4.1666,"name":"Sound2","string":"cri_se_battle_darkness_explosion"},{"time":4.2,"name":"Event","string":"blackOutBack(0, 1.2 ,0.8)"},{"time":4.2333,"name":"Event","float":2,"string":"shakeGround"},{"time":4.2333,"name":"Hit","string":"resetHitList"}]}}}